Traffic/codes/traffic.v
module Traffic_Controller(
    input clk, rst, Emergency_left, Emergency_right,
    output reg T1_Red, T1_Green, T1_Yellow, T1_Orange, T1_Right,
    output reg T2_Red, T2_Green, T2_Yellow, T2_Orange, T2_Left,
    output reg T1_WALK, T2_WALK, Buzzer_Walk
);

    // State encoding
    parameter RED = 0;
    parameter YELLOW = 1;
    parameter GREEN = 2;
    parameter ORANGE = 3;
    parameter GREEN_WITH_TURN = 4;

    // Timing parameters
    parameter RED_TIME = 60;
    parameter GREEN_TIME = 20;
    parameter TURN_TIME = 10;
    parameter YELLOW_TIME = 5;
    parameter ORANGE_TIME = 10;
    parameter BUZZER_TIME = 5;
    parameter EMERGENCY_TIME = 10;

    // State variables
    reg [2:0] state_t1;
    reg [2:0] state_t2;
    reg [5:0] timer_t1;
    reg [5:0] timer_t2;
    reg emergency;
    reg [3:0] emergency_timer;

    // Emergency detection and timer
    always @(posedge clk or posedge rst) begin
        if (rst) begin
            emergency <= 0;
            emergency_timer <= 0;
        end else begin
            if ((Emergency_left || Emergency_right) && !emergency) begin
                emergency <= 1;
                emergency_timer <= EMERGENCY_TIME;
            end else if (emergency && emergency_timer > 0) begin
                emergency_timer <= emergency_timer - 1;
                if (emergency_timer == 1) begin
                    emergency <= 0;
                end
            end
        end
    end

    // T1 State Machine
    always @(posedge clk or posedge rst) begin
        if (rst) begin
            state_t1 <= RED;
            timer_t1 <= RED_TIME;
        end else if (!emergency) begin
            if (timer_t1 > 0) timer_t1 <= timer_t1 - 1;
            else begin
                case (state_t1)
                    RED: begin
                        state_t1 <= GREEN;
                        timer_t1 <= GREEN_TIME;
                    end
                    GREEN: begin
                        state_t1 <= GREEN_WITH_TURN;
                        timer_t1 <= TURN_TIME;
                    end
                    GREEN_WITH_TURN: begin
                        state_t1 <= ORANGE;
                        timer_t1 <= ORANGE_TIME;
                    end
                    ORANGE: begin
                        state_t1 <= YELLOW;
                        timer_t1 <= YELLOW_TIME;
                    end
                    YELLOW: begin
                        state_t1 <= RED;
                        timer_t1 <= RED_TIME;
                    end
                endcase
            end
        end
    end

    // T2 State Machine (synchronized to avoid conflicts)
    always @(posedge clk or posedge rst) begin
        if (rst) begin
            state_t2 <= GREEN_WITH_TURN;
            timer_t2 <= TURN_TIME;
        end else if (!emergency) begin
            if (timer_t2 > 0) timer_t2 <= timer_t2 - 1;
            else begin
                case (state_t2)
                    RED: begin
                        if (state_t1 != GREEN && state_t1 != GREEN_WITH_TURN) begin
                            state_t2 <= GREEN;
                            timer_t2 <= GREEN_TIME;
                        end
                    end
                    GREEN: begin
                        state_t2 <= GREEN_WITH_TURN;
                        timer_t2 <= TURN_TIME;
                    end
                    GREEN_WITH_TURN: begin
                        state_t2 <= ORANGE;
                        timer_t2 <= ORANGE_TIME;
                    end
                    ORANGE: begin
                        state_t2 <= YELLOW;
                        timer_t2 <= YELLOW_TIME;
                    end
                    YELLOW: begin
                        state_t2 <= RED;
                        timer_t2 <= RED_TIME;
                    end
                endcase
            end
        end
    end

always @(*) begin
    // Default all outputs off
    {T1_Red, T1_Green, T1_Yellow, T1_Orange, T1_Right} = 0;
    {T2_Red, T2_Green, T2_Yellow, T2_Orange, T2_Left} = 0;
    T1_WALK = 0;
    T2_WALK = 0;
    Buzzer_Walk = 0;

    if (emergency) begin
         T1_Red <= 1;
        if (Emergency_right)begin
             T2_Red <= 1;end
    end else begin
        // T1 signals
        case (state_t1)
            RED: T1_Red = 1;
            GREEN: T1_Green = 1;
            GREEN_WITH_TURN: begin T1_Green = 1; T1_Right = 1; end
            ORANGE: T1_Orange = 1;
            YELLOW: T1_Yellow = 1;
        endcase

        // T2 signals
        case (state_t2)
            RED: T2_Red = 1;
            GREEN: T2_Green = 1;
            GREEN_WITH_TURN: begin T2_Green = 1; T2_Left = 1; end
            ORANGE: T2_Orange = 1;
            YELLOW: T2_Yellow = 1;
        endcase

        // Walk and buzzer logic only active when not in emergency
        if (state_t1 == RED || state_t1 == YELLOW)
            T1_WALK = 1;
        if (state_t2 == RED || state_t2 == YELLOW)
            T2_WALK = 1;

        if (((state_t1 == RED || state_t1 == YELLOW) && timer_t1 <= BUZZER_TIME) ||
            ((state_t2 == RED || state_t2 == YELLOW) && timer_t2 <= BUZZER_TIME))
            Buzzer_Walk = 1;
    end
end

endmodule

Traffic/codes/control_test.v
module control_test;
    reg clk, rst;
    reg Emergency_left, Emergency_right;
    wire T1_Red, T1_Green, T1_Yellow, T1_Orange, T1_Right;
    wire T2_Red, T2_Green, T2_Yellow, T2_Orange, T2_Left;
    wire T1_WALK, T2_WALK, Buzzer_Walk;
    wire emergency;
    wire [3:0] emergency_timer;

    // Instantiate DUT
    Traffic_Controller uut (
        .clk(clk),
        .rst(rst),
        .Emergency_left(Emergency_left),
        .Emergency_right(Emergency_right),
        .T1_Red(T1_Red), .T1_Green(T1_Green), .T1_Yellow(T1_Yellow), .T1_Orange(T1_Orange), .T1_Right(T1_Right),
        .T2_Red(T2_Red), .T2_Green(T2_Green), .T2_Yellow(T2_Yellow), .T2_Orange(T2_Orange), .T2_Left(T2_Left),
        .T1_WALK(T1_WALK), .T2_WALK(T2_WALK), .Buzzer_Walk(Buzzer_Walk)
    );
    assign emergency        = uut.emergency;
    assign emergency_timer  = uut.emergency_timer;

    // Dump waveform
    initial begin
        $dumpfile("control_test.vcd");
        $dumpvars(0, control_test);
    end

    // Clock generation: 1s period
    initial clk = 0;
    always #0.5 clk = ~clk;

    initial begin
        // Initialize
        rst = 1; Emergency_left = 0; Emergency_right = 0;
        #1 rst = 0;

        // Normal operation
        #50;

        // Emergency left active
        Emergency_left = 1;
        #10 Emergency_left = 0;

        #50;

        // Emergency right active
        Emergency_right = 1;
        #20 Emergency_right = 0;

        // Continue running to observe recovery
        #600;

        $finish;
    end

    // Monitor all relevant outputs every positive clock edge
    always @(posedge clk) begin
        $display("T=%0t | EL=%b ER=%b | T1:R=%b G=%b Y=%b O=%b RGT=%b | T2:R=%b G=%b Y=%b O=%b LFT=%b | WALK:T1=%b T2=%b | BZ=%b | EM=%b ET=%0d", 
                 $time, Emergency_left, Emergency_right,
                 T1_Red, T1_Green, T1_Yellow, T1_Orange, T1_Right,
                 T2_Red, T2_Green, T2_Yellow, T2_Orange, T2_Left,
                 T1_WALK, T2_WALK, Buzzer_Walk,
                 emergency, emergency_timer);
    end
endmodule

Traffic/codes/control_test.vcd
$date
	Wed May  7 22:35:37 2025
$end
$version
	Icarus Verilog
$end
$timescale
	1s
$end
$scope module control_test $end
$var wire 1 ! emergency $end
$var wire 4 " emergency_timer [3:0] $end
$var wire 1 # T2_Yellow $end
$var wire 1 $ T2_WALK $end
$var wire 1 % T2_Red $end
$var wire 1 & T2_Orange $end
$var wire 1 ' T2_Left $end
$var wire 1 ( T2_Green $end
$var wire 1 ) T1_Yellow $end
$var wire 1 * T1_WALK $end
$var wire 1 + T1_Right $end
$var wire 1 , T1_Red $end
$var wire 1 - T1_Orange $end
$var wire 1 . T1_Green $end
$var wire 1 / Buzzer_Walk $end
$var reg 1 0 Emergency_left $end
$var reg 1 1 Emergency_right $end
$var reg 1 2 clk $end
$var reg 1 3 rst $end
$scope module uut $end
$var wire 1 0 Emergency_left $end
$var wire 1 1 Emergency_right $end
$var wire 1 2 clk $end
$var wire 1 3 rst $end
$var reg 1 / Buzzer_Walk $end
$var reg 1 . T1_Green $end
$var reg 1 - T1_Orange $end
$var reg 1 , T1_Red $end
$var reg 1 + T1_Right $end
$var reg 1 * T1_WALK $end
$var reg 1 ) T1_Yellow $end
$var reg 1 ( T2_Green $end
$var reg 1 ' T2_Left $end
$var reg 1 & T2_Orange $end
$var reg 1 % T2_Red $end
$var reg 1 $ T2_WALK $end
$var reg 1 # T2_Yellow $end
$var reg 1 4 emergency $end
$var reg 4 5 emergency_timer [3:0] $end
$var reg 3 6 state_t1 [2:0] $end
$var reg 3 7 state_t2 [2:0] $end
$var reg 6 8 timer_t1 [5:0] $end
$var reg 6 9 timer_t2 [5:0] $end
$upscope $end
$upscope $end
$enddefinitions $end
#0
$dumpvars
b1010 9
b111100 8
b100 7
b0 6
b0 5
04
13
02
01
00
0/
0.
0-
1,
0+
1*
0)
1(
1'
0&
0%
0$
0#
b0 "
0!
$end
#1
1*
1(
1'
1,
b1001 9
b111011 8
03
12
#2
02
#3
1*
1(
1'
1,
b111010 8
b1000 9
12
#4
02
#5
1*
1(
1'
1,
b111 9
b111001 8
12
#6
02
#7
1*
1(
1'
1,
b111000 8
b110 9
12
#8
02
#9
1*
1(
1'
1,
b101 9
b110111 8
12
#10
02
#11
1*
1(
1'
1,
b110110 8
b100 9
12
#12
02
#13
1*
1(
1'
1,
b11 9
b110101 8
12
#14
02
#15
1*
1(
1'
1,
b110100 8
b10 9
12
#16
02
#17
1*
1(
1'
1,
b1 9
b110011 8
12
#18
02
#19
1*
1(
1'
1,
b110010 8
b0 9
12
#20
02
#21
1&
1*
0(
0'
1,
b1010 9
b11 7
b110001 8
12
#22
02
#23
1*
1&
1,
b110000 8
b1001 9
12
#24
02
#25
1*
1&
1,
b1000 9
b101111 8
12
#26
02
#27
1*
1&
1,
b101110 8
b111 9
12
#28
02
#29
1*
1&
1,
b110 9
b101101 8
12
#30
02
#31
1*
1&
1,
b101100 8
b101 9
12
#32
02
#33
1*
1&
1,
b100 9
b101011 8
12
#34
02
#35
1*
1&
1,
b101010 8
b11 9
12
#36
02
#37
1*
1&
1,
b10 9
b101001 8
12
#38
02
#39
1*
1&
1,
b101000 8
b1 9
12
#40
02
#41
1*
1&
1,
b0 9
b100111 8
12
#42
02
#43
1/
1$
1#
1*
0&
1,
b100110 8
b101 9
b1 7
12
#44
02
#45
1/
1$
1*
1#
1,
b100 9
b100101 8
12
#46
02
#47
1/
1$
1*
1#
1,
b100100 8
b11 9
12
#48
02
#49
1/
1$
1*
1#
1,
b10 9
b100011 8
12
#50
02
#51
0/
0$
0*
0#
1,
b1010 "
b1010 5
1!
14
b100010 8
b1 9
12
10
#52
02
#53
b1001 "
b1001 5
12
#54
02
#55
b1000 "
b1000 5
12
#56
02
#57
b111 "
b111 5
12
#58
02
#59
b110 "
b110 5
12
#60
02
#61
b101 "
b101 5
12
00
#62
02
#63
b100 "
b100 5
12
#64
02
#65
b11 "
b11 5
12
#66
02
#67
b10 "
b10 5
12
#68
02
#69
b1 "
b1 5
12
#70
02
#71
1/
1$
1*
1#
1,
0!
04
b0 "
b0 5
12
#72
02
#73
1/
1$
1*
1#
1,
b0 9
b100001 8
12
#74
02
#75
1%
0/
1$
1*
0#
1,
b100000 8
b111100 9
b0 7
12
#76
02
#77
1$
1*
1%
1,
b111011 9
b11111 8
12
#78
02
#79
1$
1*
1%
1,
b11110 8
b111010 9
12
#80
02
#81
1$
1*
1%
1,
b111001 9
b11101 8
12
#82
02
#83
1$
1*
1%
1,
b11100 8
b111000 9
12
#84
02
#85
1$
1*
1%
1,
b110111 9
b11011 8
12
#86
02
#87
1$
1*
1%
1,
b11010 8
b110110 9
12
#88
02
#89
1$
1*
1%
1,
b110101 9
b11001 8
12
#90
02
#91
1$
1*
1%
1,
b11000 8
b110100 9
12
#92
02
#93
1$
1*
1%
1,
b110011 9
b10111 8
12
#94
02
#95
1$
1*
1%
1,
b10110 8
b110010 9
12
#96
02
#97
1$
1*
1%
1,
b110001 9
b10101 8
12
#98
02
#99
1$
1*
1%
1,
b10100 8
b110000 9
12
#100
02
#101
1$
1*
1%
1,
b101111 9
b10011 8
12
#102
02
#103
1$
1*
1%
1,
b10010 8
b101110 9
12
#104
02
#105
1$
1*
1%
1,
b101101 9
b10001 8
12
#106
02
#107
1$
1*
1%
1,
b10000 8
b101100 9
12
#108
02
#109
1$
1*
1%
1,
b101011 9
b1111 8
12
#110
02
#111
b1010 "
b1010 5
1!
14
b1110 8
b101010 9
0$
0*
1%
1,
12
11
#112
02
#113
b1001 "
b1001 5
12
#114
02
#115
b1000 "
b1000 5
12
#116
02
#117
b111 "
b111 5
12
#118
02
#119
b110 "
b110 5
12
#120
02
#121
b101 "
b101 5
12
#122
02
#123
b100 "
b100 5
12
#124
02
#125
b11 "
b11 5
12
#126
02
#127
b10 "
b10 5
12
#128
02
#129
b1 "
b1 5
12
#130
02
#131
1$
1*
0!
04
b0 "
b0 5
1%
1,
12
01
#132
02
#133
1$
1*
1%
1,
b101001 9
b1101 8
12
#134
02
#135
1$
1*
1%
1,
b1100 8
b101000 9
12
#136
02
#137
1$
1*
1%
1,
b100111 9
b1011 8
12
#138
02
#139
1$
1*
1%
1,
b1010 8
b100110 9
12
#140
02
#141
1$
1*
1%
1,
b100101 9
b1001 8
12
#142
02
#143
1$
1*
1%
1,
b1000 8
b100100 9
12
#144
02
#145
1$
1*
1%
1,
b100011 9
b111 8
12
#146
02
#147
1$
1*
1%
1,
b110 8
b100010 9
12
#148
02
#149
1/
1$
1*
1%
1,
b100001 9
b101 8
12
#150
02
#151
1/
1$
1*
1%
1,
b100 8
b100000 9
12
#152
02
#153
1/
1$
1*
1%
1,
b11111 9
b11 8
12
#154
02
#155
1/
1$
1*
1%
1,
b10 8
b11110 9
12
#156
02
#157
1/
1$
1*
1%
1,
b11101 9
b1 8
12
#158
02
#159
1/
1$
1*
1%
1,
b0 8
b11100 9
12
#160
02
#161
1.
0/
1$
0*
1%
0,
b11011 9
b10100 8
b10 6
12
#162
02
#163
1$
1%
1.
b10011 8
b11010 9
12
#164
02
#165
1$
1%
1.
b11001 9
b10010 8
12
#166
02
#167
1$
1%
1.
b10001 8
b11000 9
12
#168
02
#169
1$
1%
1.
b10111 9
b10000 8
12
#170
02
#171
1$
1%
1.
b1111 8
b10110 9
12
#172
02
#173
1$
1%
1.
b10101 9
b1110 8
12
#174
02
#175
1$
1%
1.
b1101 8
b10100 9
12
#176
02
#177
1$
1%
1.
b10011 9
b1100 8
12
#178
02
#179
1$
1%
1.
b1011 8
b10010 9
12
#180
02
#181
1$
1%
1.
b10001 9
b1010 8
12
#182
02
#183
1$
1%
1.
b1001 8
b10000 9
12
#184
02
#185
1$
1%
1.
b1111 9
b1000 8
12
#186
02
#187
1$
1%
1.
b111 8
b1110 9
12
#188
02
#189
1$
1%
1.
b1101 9
b110 8
12
#190
02
#191
1$
1%
1.
b101 8
b1100 9
12
#192
02
#193
1$
1%
1.
b1011 9
b100 8
12
#194
02
#195
1$
1%
1.
b11 8
b1010 9
12
#196
02
#197
1$
1%
1.
b1001 9
b10 8
12
#198
02
#199
1$
1%
1.
b1 8
b1000 9
12
#200
02
#201
1$
1%
1.
b111 9
b0 8
12
#202
02
#203
1+
1$
1%
1.
b1010 8
b100 6
b110 9
12
#204
02
#205
1/
1$
1%
1.
1+
b101 9
b1001 8
12
#206
02
#207
1/
1$
1%
1.
1+
b1000 8
b100 9
12
#208
02
#209
1/
1$
1%
1.
1+
b11 9
b111 8
12
#210
02
#211
1/
1$
1%
1.
1+
b110 8
b10 9
12
#212
02
#213
1/
1$
1%
1.
1+
b1 9
b101 8
12
#214
02
#215
1/
1$
1%
1.
1+
b100 8
b0 9
12
#216
02
#217
1/
1$
1%
1.
1+
b11 8
12
#218
02
#219
1/
1$
1%
1.
1+
b10 8
12
#220
02
#221
1/
1$
1%
1.
1+
b1 8
12
#222
02
#223
1/
1$
1%
1.
1+
b0 8
12
#224
02
#225
1-
1/
1$
1%
0.
0+
b1010 8
b11 6
12
#226
02
#227
1(
0/
0$
0%
1-
b1001 8
b10100 9
b10 7
12
#228
02
#229
1(
1-
b10011 9
b1000 8
12
#230
02
#231
1(
1-
b111 8
b10010 9
12
#232
02
#233
1(
1-
b10001 9
b110 8
12
#234
02
#235
1(
1-
b101 8
b10000 9
12
#236
02
#237
1(
1-
b1111 9
b100 8
12
#238
02
#239
1(
1-
b11 8
b1110 9
12
#240
02
#241
1(
1-
b1101 9
b10 8
12
#242
02
#243
1(
1-
b1 8
b1100 9
12
#244
02
#245
1(
1-
b1011 9
b0 8
12
#246
02
#247
1/
1*
1)
1(
0-
b101 8
b1 6
b1010 9
12
#248
02
#249
1/
1*
1(
1)
b1001 9
b100 8
12
#250
02
#251
1/
1*
1(
1)
b11 8
b1000 9
12
#252
02
#253
1/
1*
1(
1)
b111 9
b10 8
12
#254
02
#255
1/
1*
1(
1)
b1 8
b110 9
12
#256
02
#257
1/
1*
1(
1)
b101 9
b0 8
12
#258
02
#259
1,
0/
1*
1(
0)
b111100 8
b0 6
b100 9
12
#260
02
#261
1*
1(
1,
b11 9
b111011 8
12
#262
02
#263
1*
1(
1,
b111010 8
b10 9
12
#264
02
#265
1*
1(
1,
b1 9
b111001 8
12
#266
02
#267
1*
1(
1,
b111000 8
b0 9
12
#268
02
#269
1'
1*
1(
1,
b1010 9
b100 7
b110111 8
12
#270
02
#271
1*
1(
1'
1,
b110110 8
b1001 9
12
#272
02
#273
1*
1(
1'
1,
b1000 9
b110101 8
12
#274
02
#275
1*
1(
1'
1,
b110100 8
b111 9
12
#276
02
#277
1*
1(
1'
1,
b110 9
b110011 8
12
#278
02
#279
1*
1(
1'
1,
b110010 8
b101 9
12
#280
02
#281
1*
1(
1'
1,
b100 9
b110001 8
12
#282
02
#283
1*
1(
1'
1,
b110000 8
b11 9
12
#284
02
#285
1*
1(
1'
1,
b10 9
b101111 8
12
#286
02
#287
1*
1(
1'
1,
b101110 8
b1 9
12
#288
02
#289
1*
1(
1'
1,
b0 9
b101101 8
12
#290
02
#291
1&
1*
0(
0'
1,
b101100 8
b1010 9
b11 7
12
#292
02
#293
1*
1&
1,
b1001 9
b101011 8
12
#294
02
#295
1*
1&
1,
b101010 8
b1000 9
12
#296
02
#297
1*
1&
1,
b111 9
b101001 8
12
#298
02
#299
1*
1&
1,
b101000 8
b110 9
12
#300
02
#301
1*
1&
1,
b101 9
b100111 8
12
#302
02
#303
1*
1&
1,
b100110 8
b100 9
12
#304
02
#305
1*
1&
1,
b11 9
b100101 8
12
#306
02
#307
1*
1&
1,
b100100 8
b10 9
12
#308
02
#309
1*
1&
1,
b1 9
b100011 8
12
#310
02
#311
1*
1&
1,
b100010 8
b0 9
12
#312
02
#313
1/
1$
1#
1*
0&
1,
b101 9
b1 7
b100001 8
12
#314
02
#315
1/
1$
1*
1#
1,
b100000 8
b100 9
12
#316
02
#317
1/
1$
1*
1#
1,
b11 9
b11111 8
12
#318
02
#319
1/
1$
1*
1#
1,
b11110 8
b10 9
12
#320
02
#321
1/
1$
1*
1#
1,
b1 9
b11101 8
12
#322
02
#323
1/
1$
1*
1#
1,
b11100 8
b0 9
12
#324
02
#325
1%
0/
1$
1*
0#
1,
b111100 9
b0 7
b11011 8
12
#326
02
#327
1$
1*
1%
1,
b11010 8
b111011 9
12
#328
02
#329
1$
1*
1%
1,
b111010 9
b11001 8
12
#330
02
#331
1$
1*
1%
1,
b11000 8
b111001 9
12
#332
02
#333
1$
1*
1%
1,
b111000 9
b10111 8
12
#334
02
#335
1$
1*
1%
1,
b10110 8
b110111 9
12
#336
02
#337
1$
1*
1%
1,
b110110 9
b10101 8
12
#338
02
#339
1$
1*
1%
1,
b10100 8
b110101 9
12
#340
02
#341
1$
1*
1%
1,
b110100 9
b10011 8
12
#342
02
#343
1$
1*
1%
1,
b10010 8
b110011 9
12
#344
02
#345
1$
1*
1%
1,
b110010 9
b10001 8
12
#346
02
#347
1$
1*
1%
1,
b10000 8
b110001 9
12
#348
02
#349
1$
1*
1%
1,
b110000 9
b1111 8
12
#350
02
#351
1$
1*
1%
1,
b1110 8
b101111 9
12
#352
02
#353
1$
1*
1%
1,
b101110 9
b1101 8
12
#354
02
#355
1$
1*
1%
1,
b1100 8
b101101 9
12
#356
02
#357
1$
1*
1%
1,
b101100 9
b1011 8
12
#358
02
#359
1$
1*
1%
1,
b1010 8
b101011 9
12
#360
02
#361
1$
1*
1%
1,
b101010 9
b1001 8
12
#362
02
#363
1$
1*
1%
1,
b1000 8
b101001 9
12
#364
02
#365
1$
1*
1%
1,
b101000 9
b111 8
12
#366
02
#367
1$
1*
1%
1,
b110 8
b100111 9
12
#368
02
#369
1/
1$
1*
1%
1,
b100110 9
b101 8
12
#370
02
#371
1/
1$
1*
1%
1,
b100 8
b100101 9
12
#372
02
#373
1/
1$
1*
1%
1,
b100100 9
b11 8
12
#374
02
#375
1/
1$
1*
1%
1,
b10 8
b100011 9
12
#376
02
#377
1/
1$
1*
1%
1,
b100010 9
b1 8
12
#378
02
#379
1/
1$
1*
1%
1,
b0 8
b100001 9
12
#380
02
#381
1.
0/
1$
0*
1%
0,
b100000 9
b10100 8
b10 6
12
#382
02
#383
1$
1%
1.
b10011 8
b11111 9
12
#384
02
#385
1$
1%
1.
b11110 9
b10010 8
12
#386
02
#387
1$
1%
1.
b10001 8
b11101 9
12
#388
02
#389
1$
1%
1.
b11100 9
b10000 8
12
#390
02
#391
1$
1%
1.
b1111 8
b11011 9
12
#392
02
#393
1$
1%
1.
b11010 9
b1110 8
12
#394
02
#395
1$
1%
1.
b1101 8
b11001 9
12
#396
02
#397
1$
1%
1.
b11000 9
b1100 8
12
#398
02
#399
1$
1%
1.
b1011 8
b10111 9
12
#400
02
#401
1$
1%
1.
b10110 9
b1010 8
12
#402
02
#403
1$
1%
1.
b1001 8
b10101 9
12
#404
02
#405
1$
1%
1.
b10100 9
b1000 8
12
#406
02
#407
1$
1%
1.
b111 8
b10011 9
12
#408
02
#409
1$
1%
1.
b10010 9
b110 8
12
#410
02
#411
1$
1%
1.
b101 8
b10001 9
12
#412
02
#413
1$
1%
1.
b10000 9
b100 8
12
#414
02
#415
1$
1%
1.
b11 8
b1111 9
12
#416
02
#417
1$
1%
1.
b1110 9
b10 8
12
#418
02
#419
1$
1%
1.
b1 8
b1101 9
12
#420
02
#421
1$
1%
1.
b1100 9
b0 8
12
#422
02
#423
1+
1$
1%
1.
b1010 8
b100 6
b1011 9
12
#424
02
#425
1$
1%
1.
1+
b1010 9
b1001 8
12
#426
02
#427
1$
1%
1.
1+
b1000 8
b1001 9
12
#428
02
#429
1$
1%
1.
1+
b1000 9
b111 8
12
#430
02
#431
1$
1%
1.
1+
b110 8
b111 9
12
#432
02
#433
1$
1%
1.
1+
b110 9
b101 8
12
#434
02
#435
1/
1$
1%
1.
1+
b100 8
b101 9
12
#436
02
#437
1/
1$
1%
1.
1+
b100 9
b11 8
12
#438
02
#439
1/
1$
1%
1.
1+
b10 8
b11 9
12
#440
02
#441
1/
1$
1%
1.
1+
b10 9
b1 8
12
#442
02
#443
1/
1$
1%
1.
1+
b0 8
b1 9
12
#444
02
#445
1-
1/
1$
1%
0.
0+
b0 9
b1010 8
b11 6
12
#446
02
#447
1(
0/
0$
0%
1-
b1001 8
b10100 9
b10 7
12
#448
02
#449
1(
1-
b10011 9
b1000 8
12
#450
02
#451
1(
1-
b111 8
b10010 9
12
#452
02
#453
1(
1-
b10001 9
b110 8
12
#454
02
#455
1(
1-
b101 8
b10000 9
12
#456
02
#457
1(
1-
b1111 9
b100 8
12
#458
02
#459
1(
1-
b11 8
b1110 9
12
#460
02
#461
1(
1-
b1101 9
b10 8
12
#462
02
#463
1(
1-
b1 8
b1100 9
12
#464
02
#465
1(
1-
b1011 9
b0 8
12
#466
02
#467
1/
1*
1)
1(
0-
b101 8
b1 6
b1010 9
12
#468
02
#469
1/
1*
1(
1)
b1001 9
b100 8
12
#470
02
#471
1/
1*
1(
1)
b11 8
b1000 9
12
#472
02
#473
1/
1*
1(
1)
b111 9
b10 8
12
#474
02
#475
1/
1*
1(
1)
b1 8
b110 9
12
#476
02
#477
1/
1*
1(
1)
b101 9
b0 8
12
#478
02
#479
1,
0/
1*
1(
0)
b111100 8
b0 6
b100 9
12
#480
02
#481
1*
1(
1,
b11 9
b111011 8
12
#482
02
#483
1*
1(
1,
b111010 8
b10 9
12
#484
02
#485
1*
1(
1,
b1 9
b111001 8
12
#486
02
#487
1*
1(
1,
b111000 8
b0 9
12
#488
02
#489
1'
1*
1(
1,
b1010 9
b100 7
b110111 8
12
#490
02
#491
1*
1(
1'
1,
b110110 8
b1001 9
12
#492
02
#493
1*
1(
1'
1,
b1000 9
b110101 8
12
#494
02
#495
1*
1(
1'
1,
b110100 8
b111 9
12
#496
02
#497
1*
1(
1'
1,
b110 9
b110011 8
12
#498
02
#499
1*
1(
1'
1,
b110010 8
b101 9
12
#500
02
#501
1*
1(
1'
1,
b100 9
b110001 8
12
#502
02
#503
1*
1(
1'
1,
b110000 8
b11 9
12
#504
02
#505
1*
1(
1'
1,
b10 9
b101111 8
12
#506
02
#507
1*
1(
1'
1,
b101110 8
b1 9
12
#508
02
#509
1*
1(
1'
1,
b0 9
b101101 8
12
#510
02
#511
1&
1*
0(
0'
1,
b101100 8
b1010 9
b11 7
12
#512
02
#513
1*
1&
1,
b1001 9
b101011 8
12
#514
02
#515
1*
1&
1,
b101010 8
b1000 9
12
#516
02
#517
1*
1&
1,
b111 9
b101001 8
12
#518
02
#519
1*
1&
1,
b101000 8
b110 9
12
#520
02
#521
1*
1&
1,
b101 9
b100111 8
12
#522
02
#523
1*
1&
1,
b100110 8
b100 9
12
#524
02
#525
1*
1&
1,
b11 9
b100101 8
12
#526
02
#527
1*
1&
1,
b100100 8
b10 9
12
#528
02
#529
1*
1&
1,
b1 9
b100011 8
12
#530
02
#531
1*
1&
1,
b100010 8
b0 9
12
#532
02
#533
1/
1$
1#
1*
0&
1,
b101 9
b1 7
b100001 8
12
#534
02
#535
1/
1$
1*
1#
1,
b100000 8
b100 9
12
#536
02
#537
1/
1$
1*
1#
1,
b11 9
b11111 8
12
#538
02
#539
1/
1$
1*
1#
1,
b11110 8
b10 9
12
#540
02
#541
1/
1$
1*
1#
1,
b1 9
b11101 8
12
#542
02
#543
1/
1$
1*
1#
1,
b11100 8
b0 9
12
#544
02
#545
1%
0/
1$
1*
0#
1,
b111100 9
b0 7
b11011 8
12
#546
02
#547
1$
1*
1%
1,
b11010 8
b111011 9
12
#548
02
#549
1$
1*
1%
1,
b111010 9
b11001 8
12
#550
02
#551
1$
1*
1%
1,
b11000 8
b111001 9
12
#552
02
#553
1$
1*
1%
1,
b111000 9
b10111 8
12
#554
02
#555
1$
1*
1%
1,
b10110 8
b110111 9
12
#556
02
#557
1$
1*
1%
1,
b110110 9
b10101 8
12
#558
02
#559
1$
1*
1%
1,
b10100 8
b110101 9
12
#560
02
#561
1$
1*
1%
1,
b110100 9
b10011 8
12
#562
02
#563
1$
1*
1%
1,
b10010 8
b110011 9
12
#564
02
#565
1$
1*
1%
1,
b110010 9
b10001 8
12
#566
02
#567
1$
1*
1%
1,
b10000 8
b110001 9
12
#568
02
#569
1$
1*
1%
1,
b110000 9
b1111 8
12
#570
02
#571
1$
1*
1%
1,
b1110 8
b101111 9
12
#572
02
#573
1$
1*
1%
1,
b101110 9
b1101 8
12
#574
02
#575
1$
1*
1%
1,
b1100 8
b101101 9
12
#576
02
#577
1$
1*
1%
1,
b101100 9
b1011 8
12
#578
02
#579
1$
1*
1%
1,
b1010 8
b101011 9
12
#580
02
#581
1$
1*
1%
1,
b101010 9
b1001 8
12
#582
02
#583
1$
1*
1%
1,
b1000 8
b101001 9
12
#584
02
#585
1$
1*
1%
1,
b101000 9
b111 8
12
#586
02
#587
1$
1*
1%
1,
b110 8
b100111 9
12
#588
02
#589
1/
1$
1*
1%
1,
b100110 9
b101 8
12
#590
02
#591
1/
1$
1*
1%
1,
b100 8
b100101 9
12
#592
02
#593
1/
1$
1*
1%
1,
b100100 9
b11 8
12
#594
02
#595
1/
1$
1*
1%
1,
b10 8
b100011 9
12
#596
02
#597
1/
1$
1*
1%
1,
b100010 9
b1 8
12
#598
02
#599
1/
1$
1*
1%
1,
b0 8
b100001 9
12
#600
02
#601
1.
0/
1$
0*
1%
0,
b100000 9
b10100 8
b10 6
12
#602
02
#603
1$
1%
1.
b10011 8
b11111 9
12
#604
02
#605
1$
1%
1.
b11110 9
b10010 8
12
#606
02
#607
1$
1%
1.
b10001 8
b11101 9
12
#608
02
#609
1$
1%
1.
b11100 9
b10000 8
12
#610
02
#611
1$
1%
1.
b1111 8
b11011 9
12
#612
02
#613
1$
1%
1.
b11010 9
b1110 8
12
#614
02
#615
1$
1%
1.
b1101 8
b11001 9
12
#616
02
#617
1$
1%
1.
b11000 9
b1100 8
12
#618
02
#619
1$
1%
1.
b1011 8
b10111 9
12
#620
02
#621
1$
1%
1.
b10110 9
b1010 8
12
#622
02
#623
1$
1%
1.
b1001 8
b10101 9
12
#624
02
#625
1$
1%
1.
b10100 9
b1000 8
12
#626
02
#627
1$
1%
1.
b111 8
b10011 9
12
#628
02
#629
1$
1%
1.
b10010 9
b110 8
12
#630
02
#631
1$
1%
1.
b101 8
b10001 9
12
#632
02
#633
1$
1%
1.
b10000 9
b100 8
12
#634
02
#635
1$
1%
1.
b11 8
b1111 9
12
#636
02
#637
1$
1%
1.
b1110 9
b10 8
12
#638
02
#639
1$
1%
1.
b1 8
b1101 9
12
#640
02
#641
1$
1%
1.
b1100 9
b0 8
12
#642
02
#643
1+
1$
1%
1.
b1010 8
b100 6
b1011 9
12
#644
02
#645
1$
1%
1.
1+
b1010 9
b1001 8
12
#646
02
#647
1$
1%
1.
1+
b1000 8
b1001 9
12
#648
02
#649
1$
1%
1.
1+
b1000 9
b111 8
12
#650
02
#651
1$
1%
1.
1+
b110 8
b111 9
12
#652
02
#653
1$
1%
1.
1+
b110 9
b101 8
12
#654
02
#655
1/
1$
1%
1.
1+
b100 8
b101 9
12
#656
02
#657
1/
1$
1%
1.
1+
b100 9
b11 8
12
#658
02
#659
1/
1$
1%
1.
1+
b10 8
b11 9
12
#660
02
#661
1/
1$
1%
1.
1+
b10 9
b1 8
12
#662
02
#663
1/
1$
1%
1.
1+
b0 8
b1 9
12
#664
02
