Clock/clock2.v
`timescale 1s / 1ms

// ─────────────────────────────────────────────────────────────────
// 1) Timekeeper as a four‐state FSM, with date range Jan-2020 → Apr-2025
// ─────────────────────────────────────────────────────────────────
module timekeeper(
    input             clk,
    input             reset,
    input             AM_mode,
    input             add_hour,
    input             add_minute,
    output reg [5:0]  sec,
    output reg [5:0]  min,
    output reg [5:0]  hr,
    output reg        AM_PM,
    output reg [4:0]  day,
    output reg [3:0]  month,
    output reg [11:0] year
);

  // State encoding
  localparam S_SEC  = 2'd0,
             S_MIN  = 2'd1,
             S_HR   = 2'd2,
             S_DATE = 2'd3;

  // State registers
  reg [1:0] state, next_state;

  // Next value registers
  reg [5:0] sec_next, min_next, hr_next;
  reg       AM_PM_next;
  reg [4:0] day_next;
  reg [3:0] month_next;
  reg [11:0] year_next;
  reg [5:0] days_in_month;

  // Track AM_mode changes
  reg AM_mode_prev;

  // Sequential logic
  always @(posedge clk or posedge reset) begin
    if (reset) begin
      state        <= S_SEC;
      sec          <= 0;
      min          <= 0;
      hr           <= 12;
      AM_PM        <= 0;
      day          <= 1;
      month        <= 1;
      year         <= 2020;
      AM_mode_prev <= AM_mode;
    end else begin
      state        <= next_state;
      sec          <= sec_next;
      min          <= min_next;
      hr           <= hr_next;
      AM_PM        <= AM_PM_next;
      day          <= day_next;
      month        <= month_next;
      year         <= year_next;
      AM_mode_prev <= AM_mode; // Track previous AM_mode
    end
  end

  // Combinational logic
  always @(*) begin
    // Default holds
    next_state   = state;
    sec_next     = sec;
    min_next     = min;
    hr_next      = hr;
    AM_PM_next   = AM_PM;
    day_next     = day;
    month_next   = month;
    year_next    = year;

    // Handle mode change (24h <-> 12h)
    if (AM_mode != AM_mode_prev) begin
      if (AM_mode) begin
        // 24h -> 12h
        if (hr == 0) begin
          hr_next = 12;
          AM_PM_next = 0;
        end else if (hr == 12) begin
          hr_next = 12;
          AM_PM_next = 1;
        end else if (hr > 12) begin
          hr_next = hr - 12;
          AM_PM_next = 1;
        end else begin
          hr_next = hr;
          AM_PM_next = 0;
        end
      end else begin
        // 12h -> 24h
        if (hr == 12 && AM_PM == 0)
          hr_next = 0;
        else if (hr == 12 && AM_PM == 1)
          hr_next = 12;
        else if (AM_PM == 1)
          hr_next = hr + 12;
        else
          hr_next = hr;
      end
    end

    // Main FSM
    case (state)
      S_SEC: begin
        if (sec == 6'd59) begin
          sec_next   = 0;
          next_state = S_MIN;
        end else begin
          sec_next   = sec + 1;
          next_state = S_SEC;
        end
      end

      S_MIN: begin
        if (min == 6'd59) begin
          min_next   = 0;
          next_state = S_HR;
        end else begin
          min_next   = min + 1;
          next_state = S_SEC;
        end
      end

      S_HR: begin
        if (AM_mode) begin
          if (hr == 6'd11) begin
            hr_next    = 12;
            AM_PM_next = ~AM_PM;
          end else if (hr == 6'd12) begin
            hr_next = 1;
          end else begin
            hr_next = hr + 1;
          end
        end else begin
          if (hr == 6'd23)
            hr_next = 0;
          else
            hr_next = hr + 1;
        end
        next_state = S_DATE;
      end

      S_DATE: begin
        if ((AM_mode && hr_next == 12 && AM_PM_next == 0) ||
            (!AM_mode && hr_next == 0)) begin

          // Get correct days in current month
          case (month)
            1, 3, 5, 7, 8, 10, 12: days_in_month = 31;
            4, 6, 9, 11:           days_in_month = 30;
            2: begin
              if ((year % 4 == 0 && year % 100 != 0) || (year % 400 == 0))
                days_in_month = 29;
              else
                days_in_month = 28;
            end
            default: days_in_month = 31;
          endcase

          if (day == 5'd30 && month == 4'd4 && year == 12'd2025) begin
            day_next   = 1;
            month_next = 1;
            year_next  = 2020;
          end else begin
            if (day == days_in_month) begin
              day_next = 1;
              if (month == 4'd12) begin
                month_next = 1;
                year_next  = year + 1;
              end else begin
                month_next = month + 1;
              end
            end else begin
              day_next = day + 1;
            end
          end
        end
        next_state = S_SEC;
      end
    endcase

    // Manual add minute
    if (add_minute) begin
      if (min == 6'd59) begin
        min_next = 0;
        if (AM_mode) begin
          if (hr == 6'd11) begin
            hr_next    = 12;
            AM_PM_next = ~AM_PM;
          end else if (hr == 6'd12) begin
            hr_next = 1;
          end else begin
            hr_next = hr + 1;
          end
        end else begin
          if (hr == 6'd23)
            hr_next = 0;
          else
            hr_next = hr + 1;
        end
      end else begin
        min_next = min + 1;
      end
    end

    // Manual add hour
    if (add_hour) begin
      if (AM_mode) begin
        if (hr == 6'd11) begin
          hr_next    = 12;
          AM_PM_next = ~AM_PM;
        end else if (hr == 6'd12) begin
          hr_next = 1;
        end else begin
          hr_next = hr + 1;
        end
      end else begin
        if (hr == 6'd23)
          hr_next = 0;
        else
          hr_next = hr + 1;
      end
    end
  end

endmodule

// ─────────────────────────────────────────────────────────────────
// 2) Timer
// ─────────────────────────────────────────────────────────────────
module timer_module(
    input         clk,
    input         reset,
    input         set_timer,
    input  [3:0]  timer_minutes,
    output reg    timer_buzzer,
    output [5:0]  timer_min_left,
    output [5:0]  timer_sec_left
);
  reg [9:0] timer_sec_total;
  assign timer_min_left = timer_sec_total / 60;
  assign timer_sec_left = timer_sec_total % 60;

  always @(posedge clk or posedge reset) begin
    if (reset) begin
      timer_sec_total <= 0;
      timer_buzzer    <= 0;
    end else begin
      if (set_timer && timer_sec_total == 0)
        timer_sec_total <= timer_minutes * 60;
      else if (timer_sec_total > 0) begin
        timer_sec_total <= timer_sec_total - 1;
        timer_buzzer    <= (timer_sec_total == 1);
      end else
        timer_buzzer    <= 0;
    end
  end
endmodule


// ─────────────────────────────────────────────────────────────────
// 3) Alarm
// ─────────────────────────────────────────────────────────────────
module alarm_module(
    input         clk,
    input         reset,
    input         set_alarm,
    input  [5:0]  alarm_hr,
    input  [5:0]  alarm_min,
    input  [5:0]  curr_hr,
    input  [5:0]  curr_min,
    input  [5:0]  curr_sec,
    output reg    alarm_buzzer
);
  reg [5:0] alarm_hr_reg, alarm_min_reg;

  always @(posedge clk or posedge reset) begin
    if (reset) begin
      alarm_hr_reg  <= 0;
      alarm_min_reg <= 0;
      alarm_buzzer  <= 0;
    end else begin
      if (set_alarm) begin
        alarm_hr_reg  <= alarm_hr;
        alarm_min_reg <= alarm_min;
      end
      alarm_buzzer <= (curr_hr == alarm_hr_reg &&
                       curr_min == alarm_min_reg &&
                       curr_sec == 0);
    end
  end
endmodule


// ─────────────────────────────────────────────────────────────────
// 4) Combine into digital_clock
// ─────────────────────────────────────────────────────────────────
module digital_clock(
    input         clk,
    input         reset,
    input         AM_mode,
    input         set_timer,
    input  [3:0]  timer_minutes,
    input         add_hour,
    input         add_minute,
    input         set_alarm,
    input  [5:0]  alarm_hr,
    input  [5:0]  alarm_min,
    output [5:0]  sec,
    output [5:0]  min,
    output [5:0]  hr,
    output        AM_PM,
    output [4:0]  day,
    output [3:0]  month,
    output [11:0] year,
    output        timer_buzzer,
    output        alarm_buzzer,
    output [5:0]  timer_min_left,
    output [5:0]  timer_sec_left
);
  timekeeper   tk(clk, reset, AM_mode, add_hour, add_minute,
                  sec, min, hr, AM_PM, day, month, year);

  timer_module tm(clk, reset, set_timer, timer_minutes,
                  timer_buzzer, timer_min_left, timer_sec_left);

  alarm_module am(clk, reset, set_alarm,
                  alarm_hr, alarm_min,
                  hr, min, sec,
                  alarm_buzzer);
endmodule


// ─────────────────────────────────────────────────────────────────
// 5) Top‐level with MODE FSM (IDLE → SET_TIMER → SET_ALARM → IDLE)
// ─────────────────────────────────────────────────────────────────
module clock_with_mode_fsm(
    input        clk,
    input        reset,
    input        mode_btn,
    input        add_hour,
    input        add_minute,
    input        set_timer_btn,
    input        set_alarm_btn,
    input        AM_mode,
    output [5:0] sec,
    output [5:0] min,
    output [5:0] hr,
    output       AM_PM,
    output [4:0] day,
    output [3:0] month,
    output [11:0] year,
    output       timer_buzzer,
    output       alarm_buzzer,
    output [5:0] timer_min_left,
    output [5:0] timer_sec_left
);

  // FSM states
  localparam IDLE      = 2'd0,
             SET_TIMER = 2'd1,
             SET_ALARM = 2'd2;

  reg [1:0] state, next_state;

  // State register
  always @(posedge clk or posedge reset) begin
    if (reset) state <= IDLE;
    else       state <= next_state;
  end

  // Next-state logic
  always @(*) begin
    next_state = state;
    case(state)
      IDLE:      if (mode_btn) next_state = SET_TIMER;
      SET_TIMER: if (mode_btn) next_state = SET_ALARM;
      SET_ALARM: if (mode_btn) next_state = IDLE;
    endcase
  end
  wire idle_mode_active  = (state == IDLE);   
  wire timer_mode_active = (state == SET_TIMER);
  wire alarm_mode_active = (state == SET_ALARM);

  // Adjust timer_minutes in SET_TIMER
  reg [3:0] timer_minutes;
  always @(posedge clk or posedge reset) begin
    if (reset)                              timer_minutes <= 4'd0;
    else if (timer_mode_active && add_minute) timer_minutes <= timer_minutes + 1;
    else if (timer_mode_active && add_hour)   timer_minutes <= timer_minutes + 4;
  end

  // Adjust alarm_hr/min in SET_ALARM
  reg [5:0] alarm_hr, alarm_min;
  always @(posedge clk or posedge reset) begin
    if (reset) begin
      alarm_hr  <= 6'd0;
      alarm_min <= 6'd0;
    end else if (alarm_mode_active && add_hour) begin
      alarm_hr <= (alarm_hr == (AM_mode ? 12 : 23)) ? 0 : alarm_hr + 1;
    end else if (alarm_mode_active && add_minute) begin
      alarm_min <= (alarm_min == 6'd59) ? 0 : alarm_min + 1;
    end
  end

  wire set_timer = timer_mode_active & set_timer_btn;
  wire set_alarm = alarm_mode_active & set_alarm_btn;
  wire time_add_hour=idle_mode_active?add_hour:1'b0;
  wire time_add_minute=idle_mode_active?add_minute:1'b0;
  digital_clock UDC (
    .clk(clk), .reset(reset), .AM_mode(AM_mode),
    .set_timer(set_timer),     .timer_minutes(timer_minutes),
    .add_hour(time_add_hour),           .add_minute(time_add_minute),
    .set_alarm(set_alarm),
    .alarm_hr(alarm_hr),       .alarm_min(alarm_min),
    .sec(sec), .min(min), .hr(hr), .AM_PM(AM_PM),
    .day(day), .month(month), .year(year),
    .timer_buzzer(timer_buzzer),
    .alarm_buzzer(alarm_buzzer),
    .timer_min_left(timer_min_left),
    .timer_sec_left(timer_sec_left)
  );

endmodule

Clock/timertest.v
`timescale 1s / 1ms

module test;
  reg        clk, reset;
  reg        mode_btn, add_hour, add_minute;
  reg        set_timer_btn, set_alarm_btn;
  reg        AM_mode;
  wire [5:0] sec, min, hr, timer_min_left, timer_sec_left;
  wire       AM_PM, timer_buzzer, alarm_buzzer;
  wire [4:0] day;
  wire [3:0] month;
  wire [11:0] year;

  clock_with_mode_fsm uut(
    .clk(clk), .reset(reset),
    .mode_btn(mode_btn),
    .add_hour(add_hour), .add_minute(add_minute),
    .set_timer_btn(set_timer_btn),
    .set_alarm_btn(set_alarm_btn),
    .AM_mode(AM_mode),
    .sec(sec), .min(min), .hr(hr), .AM_PM(AM_PM),
    .day(day), .month(month), .year(year),
    .timer_buzzer(timer_buzzer),
    .alarm_buzzer(alarm_buzzer),
    .timer_min_left(timer_min_left),
    .timer_sec_left(timer_sec_left)
  );

  initial begin
    // dump waves
    $dumpfile("timertest.vcd");
    $dumpvars(0,test);

    // initialize
    clk            = 0;
    reset          = 1;
    AM_mode        = 1;
    mode_btn       = 0;
    add_hour       = 0;
    add_minute     = 0;
    set_timer_btn  = 0;
    set_alarm_btn  = 0;
    #2 reset = 0;
    //Timer
    #5 mode_btn = 1; #1 mode_btn = 0;
    #5 add_minute = 1; #1 add_minute = 0;  // +1 minute
    #5 add_minute = 1; #1 add_minute = 0;  // +1 more
    #5 add_minute = 1; #1 add_minute = 0;  // +1 more
    #5 add_minute = 1; #1 add_minute = 0;  // +1 more
    #5 add_minute = 1; #1 add_minute = 0;  // +1 more
    #5 set_timer_btn = 1; #1 set_timer_btn = 0;



    #302;

    $finish;
  end

  // 0.5s clock
  always #0.5 clk = ~clk;

  // display
  always @(posedge clk) begin
    $display("MODE=%0d | %02d:%02d:%02d %s | %02d/%02d/%04d | Tleft=%02d:%02d Bz=%b | Albz=%b",
      uut.state,
      hr, min, sec, AM_mode?(AM_PM ? "PM" : "AM"):"HOURS",
      day, month, year,
      timer_min_left, timer_sec_left, timer_buzzer,
      alarm_buzzer
    );
  end

endmodule

Clock/timertest.vcd
$date
	Wed May  7 00:33:38 2025
$end
$version
	Icarus Verilog
$end
$timescale
	1ms
$end
$scope module test $end
$var wire 12 ! year [11:0] $end
$var wire 6 " timer_sec_left [5:0] $end
$var wire 6 # timer_min_left [5:0] $end
$var wire 1 $ timer_buzzer $end
$var wire 6 % sec [5:0] $end
$var wire 4 & month [3:0] $end
$var wire 6 ' min [5:0] $end
$var wire 6 ( hr [5:0] $end
$var wire 5 ) day [4:0] $end
$var wire 1 * alarm_buzzer $end
$var wire 1 + AM_PM $end
$var reg 1 , AM_mode $end
$var reg 1 - add_hour $end
$var reg 1 . add_minute $end
$var reg 1 / clk $end
$var reg 1 0 mode_btn $end
$var reg 1 1 reset $end
$var reg 1 2 set_alarm_btn $end
$var reg 1 3 set_timer_btn $end
$scope module uut $end
$var wire 1 , AM_mode $end
$var wire 1 - add_hour $end
$var wire 1 . add_minute $end
$var wire 1 / clk $end
$var wire 1 0 mode_btn $end
$var wire 1 1 reset $end
$var wire 1 4 set_alarm $end
$var wire 1 2 set_alarm_btn $end
$var wire 1 5 set_timer $end
$var wire 1 3 set_timer_btn $end
$var wire 12 6 year [11:0] $end
$var wire 6 7 timer_sec_left [5:0] $end
$var wire 1 8 timer_mode_active $end
$var wire 6 9 timer_min_left [5:0] $end
$var wire 1 $ timer_buzzer $end
$var wire 1 : time_add_minute $end
$var wire 1 ; time_add_hour $end
$var wire 6 < sec [5:0] $end
$var wire 4 = month [3:0] $end
$var wire 6 > min [5:0] $end
$var wire 1 ? idle_mode_active $end
$var wire 6 @ hr [5:0] $end
$var wire 5 A day [4:0] $end
$var wire 1 B alarm_mode_active $end
$var wire 1 * alarm_buzzer $end
$var wire 1 + AM_PM $end
$var reg 6 C alarm_hr [5:0] $end
$var reg 6 D alarm_min [5:0] $end
$var reg 2 E next_state [1:0] $end
$var reg 2 F state [1:0] $end
$var reg 4 G timer_minutes [3:0] $end
$scope module UDC $end
$var wire 1 , AM_mode $end
$var wire 1 ; add_hour $end
$var wire 1 : add_minute $end
$var wire 6 H alarm_hr [5:0] $end
$var wire 6 I alarm_min [5:0] $end
$var wire 1 / clk $end
$var wire 1 1 reset $end
$var wire 1 4 set_alarm $end
$var wire 1 5 set_timer $end
$var wire 4 J timer_minutes [3:0] $end
$var wire 12 K year [11:0] $end
$var wire 6 L timer_sec_left [5:0] $end
$var wire 6 M timer_min_left [5:0] $end
$var wire 1 $ timer_buzzer $end
$var wire 6 N sec [5:0] $end
$var wire 4 O month [3:0] $end
$var wire 6 P min [5:0] $end
$var wire 6 Q hr [5:0] $end
$var wire 5 R day [4:0] $end
$var wire 1 * alarm_buzzer $end
$var wire 1 + AM_PM $end
$scope module am $end
$var wire 6 S alarm_hr [5:0] $end
$var wire 6 T alarm_min [5:0] $end
$var wire 1 / clk $end
$var wire 1 1 reset $end
$var wire 1 4 set_alarm $end
$var wire 6 U curr_sec [5:0] $end
$var wire 6 V curr_min [5:0] $end
$var wire 6 W curr_hr [5:0] $end
$var reg 1 * alarm_buzzer $end
$var reg 6 X alarm_hr_reg [5:0] $end
$var reg 6 Y alarm_min_reg [5:0] $end
$upscope $end
$scope module tk $end
$var wire 1 , AM_mode $end
$var wire 1 ; add_hour $end
$var wire 1 : add_minute $end
$var wire 1 / clk $end
$var wire 1 1 reset $end
$var reg 1 + AM_PM $end
$var reg 1 Z AM_PM_next $end
$var reg 1 [ AM_mode_prev $end
$var reg 5 \ day [4:0] $end
$var reg 5 ] day_next [4:0] $end
$var reg 6 ^ days_in_month [5:0] $end
$var reg 6 _ hr [5:0] $end
$var reg 6 ` hr_next [5:0] $end
$var reg 6 a min [5:0] $end
$var reg 6 b min_next [5:0] $end
$var reg 4 c month [3:0] $end
$var reg 4 d month_next [3:0] $end
$var reg 2 e next_state [1:0] $end
$var reg 6 f sec [5:0] $end
$var reg 6 g sec_next [5:0] $end
$var reg 2 h state [1:0] $end
$var reg 12 i year [11:0] $end
$var reg 12 j year_next [11:0] $end
$upscope $end
$scope module tm $end
$var wire 1 / clk $end
$var wire 1 1 reset $end
$var wire 1 5 set_timer $end
$var wire 4 k timer_minutes [3:0] $end
$var wire 6 l timer_sec_left [5:0] $end
$var wire 6 m timer_min_left [5:0] $end
$var reg 1 $ timer_buzzer $end
$var reg 10 n timer_sec_total [9:0] $end
$upscope $end
$upscope $end
$upscope $end
$upscope $end
$enddefinitions $end
#0
$dumpvars
b0 n
b0 m
b0 l
b0 k
b11111100100 j
b11111100100 i
b0 h
b1 g
b0 f
b0 e
b1 d
b1 c
b0 b
b0 a
b1100 `
b1100 _
bx ^
b1 ]
b1 \
1[
0Z
b0 Y
b0 X
b1100 W
b0 V
b0 U
b0 T
b0 S
b1 R
b1100 Q
b0 P
b1 O
b0 N
b0 M
b0 L
b11111100100 K
b0 J
b0 I
b0 H
b0 G
b0 F
b0 E
b0 D
b0 C
0B
b1 A
b1100 @
1?
b0 >
b1 =
b0 <
0;
0:
b0 9
08
b0 7
b11111100100 6
05
04
03
02
11
00
0/
0.
0-
1,
0+
0*
b1 )
b1100 (
b0 '
b1 &
b0 %
0$
b0 #
b0 "
b11111100100 !
$end
#500
1/
#1000
0/
#1500
1/
#2000
0/
01
#2500
b10 g
b1 %
b1 <
b1 N
b1 U
b1 f
1/
#3000
0/
#3500
b11 g
b10 %
b10 <
b10 N
b10 U
b10 f
1/
#4000
0/
#4500
b100 g
b11 %
b11 <
b11 N
b11 U
b11 f
1/
#5000
0/
#5500
b101 g
b100 %
b100 <
b100 N
b100 U
b100 f
1/
#6000
0/
#6500
b110 g
b101 %
b101 <
b101 N
b101 U
b101 f
1/
#7000
b1 E
0/
10
#7500
b111 g
b10 E
b110 %
b110 <
b110 N
b110 U
b110 f
0?
18
b1 F
1/
#8000
b1 E
0/
00
#8500
b1000 g
b111 %
b111 <
b111 N
b111 U
b111 f
1/
#9000
0/
#9500
b1001 g
b1000 %
b1000 <
b1000 N
b1000 U
b1000 f
1/
#10000
0/
#10500
b1010 g
b1001 %
b1001 <
b1001 N
b1001 U
b1001 f
1/
#11000
0/
#11500
b1011 g
b1010 %
b1010 <
b1010 N
b1010 U
b1010 f
1/
#12000
0/
#12500
b1100 g
b1011 %
b1011 <
b1011 N
b1011 U
b1011 f
1/
#13000
0/
1.
#13500
b1101 g
b1100 %
b1100 <
b1100 N
b1100 U
b1100 f
b1 G
b1 J
b1 k
1/
#14000
0/
0.
#14500
b1110 g
b1101 %
b1101 <
b1101 N
b1101 U
b1101 f
1/
#15000
0/
#15500
b1111 g
b1110 %
b1110 <
b1110 N
b1110 U
b1110 f
1/
#16000
0/
#16500
b10000 g
b1111 %
b1111 <
b1111 N
b1111 U
b1111 f
1/
#17000
0/
#17500
b10001 g
b10000 %
b10000 <
b10000 N
b10000 U
b10000 f
1/
#18000
0/
#18500
b10010 g
b10001 %
b10001 <
b10001 N
b10001 U
b10001 f
1/
#19000
0/
1.
#19500
b10011 g
b10010 %
b10010 <
b10010 N
b10010 U
b10010 f
b10 G
b10 J
b10 k
1/
#20000
0/
0.
#20500
b10100 g
b10011 %
b10011 <
b10011 N
b10011 U
b10011 f
1/
#21000
0/
#21500
b10101 g
b10100 %
b10100 <
b10100 N
b10100 U
b10100 f
1/
#22000
0/
#22500
b10110 g
b10101 %
b10101 <
b10101 N
b10101 U
b10101 f
1/
#23000
0/
#23500
b10111 g
b10110 %
b10110 <
b10110 N
b10110 U
b10110 f
1/
#24000
0/
#24500
b11000 g
b10111 %
b10111 <
b10111 N
b10111 U
b10111 f
1/
#25000
0/
1.
#25500
b11001 g
b11000 %
b11000 <
b11000 N
b11000 U
b11000 f
b11 G
b11 J
b11 k
1/
#26000
0/
0.
#26500
b11010 g
b11001 %
b11001 <
b11001 N
b11001 U
b11001 f
1/
#27000
0/
#27500
b11011 g
b11010 %
b11010 <
b11010 N
b11010 U
b11010 f
1/
#28000
0/
#28500
b11100 g
b11011 %
b11011 <
b11011 N
b11011 U
b11011 f
1/
#29000
0/
#29500
b11101 g
b11100 %
b11100 <
b11100 N
b11100 U
b11100 f
1/
#30000
0/
#30500
b11110 g
b11101 %
b11101 <
b11101 N
b11101 U
b11101 f
1/
#31000
0/
1.
#31500
b11111 g
b11110 %
b11110 <
b11110 N
b11110 U
b11110 f
b100 G
b100 J
b100 k
1/
#32000
0/
0.
#32500
b100000 g
b11111 %
b11111 <
b11111 N
b11111 U
b11111 f
1/
#33000
0/
#33500
b100001 g
b100000 %
b100000 <
b100000 N
b100000 U
b100000 f
1/
#34000
0/
#34500
b100010 g
b100001 %
b100001 <
b100001 N
b100001 U
b100001 f
1/
#35000
0/
#35500
b100011 g
b100010 %
b100010 <
b100010 N
b100010 U
b100010 f
1/
#36000
0/
#36500
b100100 g
b100011 %
b100011 <
b100011 N
b100011 U
b100011 f
1/
#37000
0/
1.
#37500
b100101 g
b100100 %
b100100 <
b100100 N
b100100 U
b100100 f
b101 G
b101 J
b101 k
1/
#38000
0/
0.
#38500
b100110 g
b100101 %
b100101 <
b100101 N
b100101 U
b100101 f
1/
#39000
0/
#39500
b100111 g
b100110 %
b100110 <
b100110 N
b100110 U
b100110 f
1/
#40000
0/
#40500
b101000 g
b100111 %
b100111 <
b100111 N
b100111 U
b100111 f
1/
#41000
0/
#41500
b101001 g
b101000 %
b101000 <
b101000 N
b101000 U
b101000 f
1/
#42000
0/
#42500
b101010 g
b101001 %
b101001 <
b101001 N
b101001 U
b101001 f
1/
#43000
15
0/
13
#43500
b101011 g
b101 #
b101 9
b101 M
b101 m
b101010 %
b101010 <
b101010 N
b101010 U
b101010 f
b100101100 n
1/
#44000
05
0/
03
#44500
b100 #
b100 9
b100 M
b100 m
b111011 "
b111011 7
b111011 L
b111011 l
b101100 g
b100101011 n
b101011 %
b101011 <
b101011 N
b101011 U
b101011 f
1/
#45000
0/
#45500
b101101 g
b111010 "
b111010 7
b111010 L
b111010 l
b101100 %
b101100 <
b101100 N
b101100 U
b101100 f
b100101010 n
1/
#46000
0/
#46500
b111001 "
b111001 7
b111001 L
b111001 l
b101110 g
b100101001 n
b101101 %
b101101 <
b101101 N
b101101 U
b101101 f
1/
#47000
0/
#47500
b101111 g
b111000 "
b111000 7
b111000 L
b111000 l
b101110 %
b101110 <
b101110 N
b101110 U
b101110 f
b100101000 n
1/
#48000
0/
#48500
b110111 "
b110111 7
b110111 L
b110111 l
b110000 g
b100100111 n
b101111 %
b101111 <
b101111 N
b101111 U
b101111 f
1/
#49000
0/
#49500
b110001 g
b110110 "
b110110 7
b110110 L
b110110 l
b110000 %
b110000 <
b110000 N
b110000 U
b110000 f
b100100110 n
1/
#50000
0/
#50500
b110101 "
b110101 7
b110101 L
b110101 l
b110010 g
b100100101 n
b110001 %
b110001 <
b110001 N
b110001 U
b110001 f
1/
#51000
0/
#51500
b110011 g
b110100 "
b110100 7
b110100 L
b110100 l
b110010 %
b110010 <
b110010 N
b110010 U
b110010 f
b100100100 n
1/
#52000
0/
#52500
b110011 "
b110011 7
b110011 L
b110011 l
b110100 g
b100100011 n
b110011 %
b110011 <
b110011 N
b110011 U
b110011 f
1/
#53000
0/
#53500
b110101 g
b110010 "
b110010 7
b110010 L
b110010 l
b110100 %
b110100 <
b110100 N
b110100 U
b110100 f
b100100010 n
1/
#54000
0/
#54500
b110001 "
b110001 7
b110001 L
b110001 l
b110110 g
b100100001 n
b110101 %
b110101 <
b110101 N
b110101 U
b110101 f
1/
#55000
0/
#55500
b110111 g
b110000 "
b110000 7
b110000 L
b110000 l
b110110 %
b110110 <
b110110 N
b110110 U
b110110 f
b100100000 n
1/
#56000
0/
#56500
b101111 "
b101111 7
b101111 L
b101111 l
b111000 g
b100011111 n
b110111 %
b110111 <
b110111 N
b110111 U
b110111 f
1/
#57000
0/
#57500
b111001 g
b101110 "
b101110 7
b101110 L
b101110 l
b111000 %
b111000 <
b111000 N
b111000 U
b111000 f
b100011110 n
1/
#58000
0/
#58500
b101101 "
b101101 7
b101101 L
b101101 l
b111010 g
b100011101 n
b111001 %
b111001 <
b111001 N
b111001 U
b111001 f
1/
#59000
0/
#59500
b111011 g
b101100 "
b101100 7
b101100 L
b101100 l
b111010 %
b111010 <
b111010 N
b111010 U
b111010 f
b100011100 n
1/
#60000
0/
#60500
b101011 "
b101011 7
b101011 L
b101011 l
b1 e
b0 g
b100011011 n
b111011 %
b111011 <
b111011 N
b111011 U
b111011 f
1/
#61000
0/
#61500
b0 e
b1 b
b101010 "
b101010 7
b101010 L
b101010 l
b0 %
b0 <
b0 N
b0 U
b0 f
b1 h
b100011010 n
1/
#62000
0/
#62500
b101001 "
b101001 7
b101001 L
b101001 l
b1 g
b100011001 n
b1 '
b1 >
b1 P
b1 V
b1 a
b0 h
1/
#63000
0/
#63500
b10 g
b101000 "
b101000 7
b101000 L
b101000 l
b1 %
b1 <
b1 N
b1 U
b1 f
b100011000 n
1/
#64000
0/
#64500
b100111 "
b100111 7
b100111 L
b100111 l
b11 g
b100010111 n
b10 %
b10 <
b10 N
b10 U
b10 f
1/
#65000
0/
#65500
b100 g
b100110 "
b100110 7
b100110 L
b100110 l
b11 %
b11 <
b11 N
b11 U
b11 f
b100010110 n
1/
#66000
0/
#66500
b100101 "
b100101 7
b100101 L
b100101 l
b101 g
b100010101 n
b100 %
b100 <
b100 N
b100 U
b100 f
1/
#67000
0/
#67500
b110 g
b100100 "
b100100 7
b100100 L
b100100 l
b101 %
b101 <
b101 N
b101 U
b101 f
b100010100 n
1/
#68000
0/
#68500
b100011 "
b100011 7
b100011 L
b100011 l
b111 g
b100010011 n
b110 %
b110 <
b110 N
b110 U
b110 f
1/
#69000
0/
#69500
b1000 g
b100010 "
b100010 7
b100010 L
b100010 l
b111 %
b111 <
b111 N
b111 U
b111 f
b100010010 n
1/
#70000
0/
#70500
b100001 "
b100001 7
b100001 L
b100001 l
b1001 g
b100010001 n
b1000 %
b1000 <
b1000 N
b1000 U
b1000 f
1/
#71000
0/
#71500
b1010 g
b100000 "
b100000 7
b100000 L
b100000 l
b1001 %
b1001 <
b1001 N
b1001 U
b1001 f
b100010000 n
1/
#72000
0/
#72500
b11111 "
b11111 7
b11111 L
b11111 l
b1011 g
b100001111 n
b1010 %
b1010 <
b1010 N
b1010 U
b1010 f
1/
#73000
0/
#73500
b1100 g
b11110 "
b11110 7
b11110 L
b11110 l
b1011 %
b1011 <
b1011 N
b1011 U
b1011 f
b100001110 n
1/
#74000
0/
#74500
b11101 "
b11101 7
b11101 L
b11101 l
b1101 g
b100001101 n
b1100 %
b1100 <
b1100 N
b1100 U
b1100 f
1/
#75000
0/
#75500
b1110 g
b11100 "
b11100 7
b11100 L
b11100 l
b1101 %
b1101 <
b1101 N
b1101 U
b1101 f
b100001100 n
1/
#76000
0/
#76500
b11011 "
b11011 7
b11011 L
b11011 l
b1111 g
b100001011 n
b1110 %
b1110 <
b1110 N
b1110 U
b1110 f
1/
#77000
0/
#77500
b10000 g
b11010 "
b11010 7
b11010 L
b11010 l
b1111 %
b1111 <
b1111 N
b1111 U
b1111 f
b100001010 n
1/
#78000
0/
#78500
b11001 "
b11001 7
b11001 L
b11001 l
b10001 g
b100001001 n
b10000 %
b10000 <
b10000 N
b10000 U
b10000 f
1/
#79000
0/
#79500
b10010 g
b11000 "
b11000 7
b11000 L
b11000 l
b10001 %
b10001 <
b10001 N
b10001 U
b10001 f
b100001000 n
1/
#80000
0/
#80500
b10111 "
b10111 7
b10111 L
b10111 l
b10011 g
b100000111 n
b10010 %
b10010 <
b10010 N
b10010 U
b10010 f
1/
#81000
0/
#81500
b10100 g
b10110 "
b10110 7
b10110 L
b10110 l
b10011 %
b10011 <
b10011 N
b10011 U
b10011 f
b100000110 n
1/
#82000
0/
#82500
b10101 "
b10101 7
b10101 L
b10101 l
b10101 g
b100000101 n
b10100 %
b10100 <
b10100 N
b10100 U
b10100 f
1/
#83000
0/
#83500
b10110 g
b10100 "
b10100 7
b10100 L
b10100 l
b10101 %
b10101 <
b10101 N
b10101 U
b10101 f
b100000100 n
1/
#84000
0/
#84500
b10011 "
b10011 7
b10011 L
b10011 l
b10111 g
b100000011 n
b10110 %
b10110 <
b10110 N
b10110 U
b10110 f
1/
#85000
0/
#85500
b11000 g
b10010 "
b10010 7
b10010 L
b10010 l
b10111 %
b10111 <
b10111 N
b10111 U
b10111 f
b100000010 n
1/
#86000
0/
#86500
b10001 "
b10001 7
b10001 L
b10001 l
b11001 g
b100000001 n
b11000 %
b11000 <
b11000 N
b11000 U
b11000 f
1/
#87000
0/
#87500
b11010 g
b10000 "
b10000 7
b10000 L
b10000 l
b11001 %
b11001 <
b11001 N
b11001 U
b11001 f
b100000000 n
1/
#88000
0/
#88500
b1111 "
b1111 7
b1111 L
b1111 l
b11011 g
b11111111 n
b11010 %
b11010 <
b11010 N
b11010 U
b11010 f
1/
#89000
0/
#89500
b11100 g
b1110 "
b1110 7
b1110 L
b1110 l
b11011 %
b11011 <
b11011 N
b11011 U
b11011 f
b11111110 n
1/
#90000
0/
#90500
b1101 "
b1101 7
b1101 L
b1101 l
b11101 g
b11111101 n
b11100 %
b11100 <
b11100 N
b11100 U
b11100 f
1/
#91000
0/
#91500
b11110 g
b1100 "
b1100 7
b1100 L
b1100 l
b11101 %
b11101 <
b11101 N
b11101 U
b11101 f
b11111100 n
1/
#92000
0/
#92500
b1011 "
b1011 7
b1011 L
b1011 l
b11111 g
b11111011 n
b11110 %
b11110 <
b11110 N
b11110 U
b11110 f
1/
#93000
0/
#93500
b100000 g
b1010 "
b1010 7
b1010 L
b1010 l
b11111 %
b11111 <
b11111 N
b11111 U
b11111 f
b11111010 n
1/
#94000
0/
