Clock/clock2.v
`timescale 1s / 1ms

// ─────────────────────────────────────────────────────────────────
// 1) Timekeeper as a four‐state FSM, with date range Jan-2020 → Apr-2025
// ─────────────────────────────────────────────────────────────────
module timekeeper(
    input             clk,
    input             reset,
    input             AM_mode,
    input             add_hour,
    input             add_minute,
    output reg [5:0]  sec,
    output reg [5:0]  min,
    output reg [5:0]  hr,
    output reg        AM_PM,
    output reg [4:0]  day,
    output reg [3:0]  month,
    output reg [11:0] year
);

  // State encoding
  localparam S_SEC  = 2'd0,
             S_MIN  = 2'd1,
             S_HR   = 2'd2,
             S_DATE = 2'd3;

  // State registers
  reg [1:0] state, next_state;

  // Next value registers
  reg [5:0] sec_next, min_next, hr_next;
  reg       AM_PM_next;
  reg [4:0] day_next;
  reg [3:0] month_next;
  reg [11:0] year_next;
  reg [5:0] days_in_month;

  // Track AM_mode changes
  reg AM_mode_prev;

  // Sequential logic
  always @(posedge clk or posedge reset) begin
    if (reset) begin
      state        <= S_SEC;
      sec          <= 0;
      min          <= 0;
      hr           <= 12;
      AM_PM        <= 0;
      day          <= 1;
      month        <= 1;
      year         <= 2020;
      AM_mode_prev <= AM_mode;
    end else begin
      state        <= next_state;
      sec          <= sec_next;
      min          <= min_next;
      hr           <= hr_next;
      AM_PM        <= AM_PM_next;
      day          <= day_next;
      month        <= month_next;
      year         <= year_next;
      AM_mode_prev <= AM_mode; // Track previous AM_mode
    end
  end

  // Combinational logic
  always @(*) begin
    // Default holds
    next_state   = state;
    sec_next     = sec;
    min_next     = min;
    hr_next      = hr;
    AM_PM_next   = AM_PM;
    day_next     = day;
    month_next   = month;
    year_next    = year;

    // Handle mode change (24h <-> 12h)
    if (AM_mode != AM_mode_prev) begin
      if (AM_mode) begin
        // 24h -> 12h
        if (hr == 0) begin
          hr_next = 12;
          AM_PM_next = 0;
        end else if (hr == 12) begin
          hr_next = 12;
          AM_PM_next = 1;
        end else if (hr > 12) begin
          hr_next = hr - 12;
          AM_PM_next = 1;
        end else begin
          hr_next = hr;
          AM_PM_next = 0;
        end
      end else begin
        // 12h -> 24h
        if (hr == 12 && AM_PM == 0)
          hr_next = 0;
        else if (hr == 12 && AM_PM == 1)
          hr_next = 12;
        else if (AM_PM == 1)
          hr_next = hr + 12;
        else
          hr_next = hr;
      end
    end

    // Main FSM
    case (state)
      S_SEC: begin
        if (sec == 6'd59) begin
          sec_next   = 0;
          next_state = S_MIN;
        end else begin
          sec_next   = sec + 1;
          next_state = S_SEC;
        end
      end

      S_MIN: begin
        if (min == 6'd59) begin
          min_next   = 0;
          next_state = S_HR;
        end else begin
          min_next   = min + 1;
          next_state = S_SEC;
        end
      end

      S_HR: begin
        if (AM_mode) begin
          if (hr == 6'd11) begin
            hr_next    = 12;
            AM_PM_next = ~AM_PM;
          end else if (hr == 6'd12) begin
            hr_next = 1;
          end else begin
            hr_next = hr + 1;
          end
        end else begin
          if (hr == 6'd23)
            hr_next = 0;
          else
            hr_next = hr + 1;
        end
        next_state = S_DATE;
      end

      S_DATE: begin
        if ((AM_mode && hr_next == 12 && AM_PM_next == 0) ||
            (!AM_mode && hr_next == 0)) begin

          // Get correct days in current month
          case (month)
            1, 3, 5, 7, 8, 10, 12: days_in_month = 31;
            4, 6, 9, 11:           days_in_month = 30;
            2: begin
              if ((year % 4 == 0 && year % 100 != 0) || (year % 400 == 0))
                days_in_month = 29;
              else
                days_in_month = 28;
            end
            default: days_in_month = 31;
          endcase

          if (day == 5'd30 && month == 4'd4 && year == 12'd2025) begin
            day_next   = 1;
            month_next = 1;
            year_next  = 2020;
          end else begin
            if (day == days_in_month) begin
              day_next = 1;
              if (month == 4'd12) begin
                month_next = 1;
                year_next  = year + 1;
              end else begin
                month_next = month + 1;
              end
            end else begin
              day_next = day + 1;
            end
          end
        end
        next_state = S_SEC;
      end
    endcase

    // Manual add minute
    if (add_minute) begin
      if (min == 6'd59) begin
        min_next = 0;
        if (AM_mode) begin
          if (hr == 6'd11) begin
            hr_next    = 12;
            AM_PM_next = ~AM_PM;
          end else if (hr == 6'd12) begin
            hr_next = 1;
          end else begin
            hr_next = hr + 1;
          end
        end else begin
          if (hr == 6'd23)
            hr_next = 0;
          else
            hr_next = hr + 1;
        end
      end else begin
        min_next = min + 1;
      end
    end

    // Manual add hour
    if (add_hour) begin
      if (AM_mode) begin
        if (hr == 6'd11) begin
          hr_next    = 12;
          AM_PM_next = ~AM_PM;
        end else if (hr == 6'd12) begin
          hr_next = 1;
        end else begin
          hr_next = hr + 1;
        end
      end else begin
        if (hr == 6'd23)
          hr_next = 0;
        else
          hr_next = hr + 1;
      end
    end
  end

endmodule

// ─────────────────────────────────────────────────────────────────
// 2) Timer
// ─────────────────────────────────────────────────────────────────
module timer_module(
    input         clk,
    input         reset,
    input         set_timer,
    input  [3:0]  timer_minutes,
    output reg    timer_buzzer,
    output [5:0]  timer_min_left,
    output [5:0]  timer_sec_left
);
  reg [9:0] timer_sec_total;
  assign timer_min_left = timer_sec_total / 60;
  assign timer_sec_left = timer_sec_total % 60;

  always @(posedge clk or posedge reset) begin
    if (reset) begin
      timer_sec_total <= 0;
      timer_buzzer    <= 0;
    end else begin
      if (set_timer && timer_sec_total == 0)
        timer_sec_total <= timer_minutes * 60;
      else if (timer_sec_total > 0) begin
        timer_sec_total <= timer_sec_total - 1;
        timer_buzzer    <= (timer_sec_total == 1);
      end else
        timer_buzzer    <= 0;
    end
  end
endmodule


// ─────────────────────────────────────────────────────────────────
// 3) Alarm
// ─────────────────────────────────────────────────────────────────
module alarm_module(
    input         clk,
    input         reset,
    input         set_alarm,
    input  [5:0]  alarm_hr,
    input  [5:0]  alarm_min,
    input  [5:0]  curr_hr,
    input  [5:0]  curr_min,
    input  [5:0]  curr_sec,
    output reg    alarm_buzzer
);
  reg [5:0] alarm_hr_reg, alarm_min_reg;

  always @(posedge clk or posedge reset) begin
    if (reset) begin
      alarm_hr_reg  <= 0;
      alarm_min_reg <= 0;
      alarm_buzzer  <= 0;
    end else begin
      if (set_alarm) begin
        alarm_hr_reg  <= alarm_hr;
        alarm_min_reg <= alarm_min;
      end
      alarm_buzzer <= (curr_hr == alarm_hr_reg &&
                       curr_min == alarm_min_reg &&
                       curr_sec == 0);
    end
  end
endmodule


// ─────────────────────────────────────────────────────────────────
// 4) Combine into digital_clock
// ─────────────────────────────────────────────────────────────────
module digital_clock(
    input         clk,
    input         reset,
    input         AM_mode,
    input         set_timer,
    input  [3:0]  timer_minutes,
    input         add_hour,
    input         add_minute,
    input         set_alarm,
    input  [5:0]  alarm_hr,
    input  [5:0]  alarm_min,
    output [5:0]  sec,
    output [5:0]  min,
    output [5:0]  hr,
    output        AM_PM,
    output [4:0]  day,
    output [3:0]  month,
    output [11:0] year,
    output        timer_buzzer,
    output        alarm_buzzer,
    output [5:0]  timer_min_left,
    output [5:0]  timer_sec_left
);
  timekeeper   tk(clk, reset, AM_mode, add_hour, add_minute,
                  sec, min, hr, AM_PM, day, month, year);

  timer_module tm(clk, reset, set_timer, timer_minutes,
                  timer_buzzer, timer_min_left, timer_sec_left);

  alarm_module am(clk, reset, set_alarm,
                  alarm_hr, alarm_min,
                  hr, min, sec,
                  alarm_buzzer);
endmodule


// ─────────────────────────────────────────────────────────────────
// 5) Top‐level with MODE FSM (IDLE → SET_TIMER → SET_ALARM → IDLE)
// ─────────────────────────────────────────────────────────────────
module clock_with_mode_fsm(
    input        clk,
    input        reset,
    input        mode_btn,
    input        add_hour,
    input        add_minute,
    input        set_timer_btn,
    input        set_alarm_btn,
    input        AM_mode,
    output [5:0] sec,
    output [5:0] min,
    output [5:0] hr,
    output       AM_PM,
    output [4:0] day,
    output [3:0] month,
    output [11:0] year,
    output       timer_buzzer,
    output       alarm_buzzer,
    output [5:0] timer_min_left,
    output [5:0] timer_sec_left
);

  // FSM states
  localparam IDLE      = 2'd0,
             SET_TIMER = 2'd1,
             SET_ALARM = 2'd2;

  reg [1:0] state, next_state;

  // State register
  always @(posedge clk or posedge reset) begin
    if (reset) state <= IDLE;
    else       state <= next_state;
  end

  // Next-state logic
  always @(*) begin
    next_state = state;
    case(state)
      IDLE:      if (mode_btn) next_state = SET_TIMER;
      SET_TIMER: if (mode_btn) next_state = SET_ALARM;
      SET_ALARM: if (mode_btn) next_state = IDLE;
    endcase
  end
  wire idle_mode_active  = (state == IDLE);   
  wire timer_mode_active = (state == SET_TIMER);
  wire alarm_mode_active = (state == SET_ALARM);

  // Adjust timer_minutes in SET_TIMER
  reg [3:0] timer_minutes;
  always @(posedge clk or posedge reset) begin
    if (reset)                              timer_minutes <= 4'd0;
    else if (timer_mode_active && add_minute) timer_minutes <= timer_minutes + 1;
    else if (timer_mode_active && add_hour)   timer_minutes <= timer_minutes + 4;
  end

  // Adjust alarm_hr/min in SET_ALARM
  reg [5:0] alarm_hr, alarm_min;
  always @(posedge clk or posedge reset) begin
    if (reset) begin
      alarm_hr  <= 6'd0;
      alarm_min <= 6'd0;
    end else if (alarm_mode_active && add_hour) begin
      alarm_hr <= (alarm_hr == (AM_mode ? 12 : 23)) ? 0 : alarm_hr + 1;
    end else if (alarm_mode_active && add_minute) begin
      alarm_min <= (alarm_min == 6'd59) ? 0 : alarm_min + 1;
    end
  end

  wire set_timer = timer_mode_active & set_timer_btn;
  wire set_alarm = alarm_mode_active & set_alarm_btn;
  wire time_add_hour=idle_mode_active?add_hour:1'b0;
  wire time_add_minute=idle_mode_active?add_minute:1'b0;
  digital_clock UDC (
    .clk(clk), .reset(reset), .AM_mode(AM_mode),
    .set_timer(set_timer),     .timer_minutes(timer_minutes),
    .add_hour(time_add_hour),           .add_minute(time_add_minute),
    .set_alarm(set_alarm),
    .alarm_hr(alarm_hr),       .alarm_min(alarm_min),
    .sec(sec), .min(min), .hr(hr), .AM_PM(AM_PM),
    .day(day), .month(month), .year(year),
    .timer_buzzer(timer_buzzer),
    .alarm_buzzer(alarm_buzzer),
    .timer_min_left(timer_min_left),
    .timer_sec_left(timer_sec_left)
  );

endmodule

Clock/timertest.v
`timescale 1s / 1ms

module test;
  reg        clk, reset;
  reg        mode_btn, add_hour, add_minute;
  reg        set_timer_btn, set_alarm_btn;
  reg        AM_mode;
  wire [5:0] sec, min, hr, timer_min_left, timer_sec_left;
  wire       AM_PM, timer_buzzer, alarm_buzzer;
  wire [4:0] day;
  wire [3:0] month;
  wire [11:0] year;

  clock_with_mode_fsm uut(
    .clk(clk), .reset(reset),
    .mode_btn(mode_btn),
    .add_hour(add_hour), .add_minute(add_minute),
    .set_timer_btn(set_timer_btn),
    .set_alarm_btn(set_alarm_btn),
    .AM_mode(AM_mode),
    .sec(sec), .min(min), .hr(hr), .AM_PM(AM_PM),
    .day(day), .month(month), .year(year),
    .timer_buzzer(timer_buzzer),
    .alarm_buzzer(alarm_buzzer),
    .timer_min_left(timer_min_left),
    .timer_sec_left(timer_sec_left)
  );
integer i;
integer timee=5;
  initial begin
    // dump waves
    $dumpfile("timertest.vcd");
    $dumpvars(0,test);

    // initialize
    clk            = 0;
    reset          = 1;
    AM_mode        = 1;
    mode_btn       = 0;
    add_hour       = 0;
    add_minute     = 0;
    set_timer_btn  = 0;
    set_alarm_btn  = 0;
    #2 reset = 0;
    //Timer
    #5 mode_btn = 1; #1 mode_btn = 0;
    for(i=0;i<timee;i=i+1)begin
    #5 add_minute = 1; #1 add_minute = 0;
    end
    #5 set_timer_btn = 1; #1 set_timer_btn = 0;



    #(timee*60+2);

    $finish;
  end

  // 0.5s clock
  always #0.5 clk = ~clk;

  // display
  always @(posedge clk) begin
    $display("MODE=%0d | %02d:%02d:%02d %s | %02d/%02d/%04d | Tleft=%02d:%02d Bz=%b | Albz=%b",
      uut.state,
      hr, min, sec, AM_mode?(AM_PM ? "PM" : "AM"):"HOURS",
      day, month, year,
      timer_min_left, timer_sec_left, timer_buzzer,
      alarm_buzzer
    );
  end

endmodule

Clock/timertest.vcd
$date
	Wed May  7 00:40:37 2025
$end
$version
	Icarus Verilog
$end
$timescale
	1ms
$end
$scope module test $end
$var wire 12 ! year [11:0] $end
$var wire 6 " timer_sec_left [5:0] $end
$var wire 6 # timer_min_left [5:0] $end
$var wire 1 $ timer_buzzer $end
$var wire 6 % sec [5:0] $end
$var wire 4 & month [3:0] $end
$var wire 6 ' min [5:0] $end
$var wire 6 ( hr [5:0] $end
$var wire 5 ) day [4:0] $end
$var wire 1 * alarm_buzzer $end
$var wire 1 + AM_PM $end
$var reg 1 , AM_mode $end
$var reg 1 - add_hour $end
$var reg 1 . add_minute $end
$var reg 1 / clk $end
$var reg 1 0 mode_btn $end
$var reg 1 1 reset $end
$var reg 1 2 set_alarm_btn $end
$var reg 1 3 set_timer_btn $end
$var integer 32 4 i [31:0] $end
$var integer 32 5 timee [31:0] $end
$scope module uut $end
$var wire 1 , AM_mode $end
$var wire 1 - add_hour $end
$var wire 1 . add_minute $end
$var wire 1 / clk $end
$var wire 1 0 mode_btn $end
$var wire 1 1 reset $end
$var wire 1 6 set_alarm $end
$var wire 1 2 set_alarm_btn $end
$var wire 1 7 set_timer $end
$var wire 1 3 set_timer_btn $end
$var wire 12 8 year [11:0] $end
$var wire 6 9 timer_sec_left [5:0] $end
$var wire 1 : timer_mode_active $end
$var wire 6 ; timer_min_left [5:0] $end
$var wire 1 $ timer_buzzer $end
$var wire 1 < time_add_minute $end
$var wire 1 = time_add_hour $end
$var wire 6 > sec [5:0] $end
$var wire 4 ? month [3:0] $end
$var wire 6 @ min [5:0] $end
$var wire 1 A idle_mode_active $end
$var wire 6 B hr [5:0] $end
$var wire 5 C day [4:0] $end
$var wire 1 D alarm_mode_active $end
$var wire 1 * alarm_buzzer $end
$var wire 1 + AM_PM $end
$var reg 6 E alarm_hr [5:0] $end
$var reg 6 F alarm_min [5:0] $end
$var reg 2 G next_state [1:0] $end
$var reg 2 H state [1:0] $end
$var reg 4 I timer_minutes [3:0] $end
$scope module UDC $end
$var wire 1 , AM_mode $end
$var wire 1 = add_hour $end
$var wire 1 < add_minute $end
$var wire 6 J alarm_hr [5:0] $end
$var wire 6 K alarm_min [5:0] $end
$var wire 1 / clk $end
$var wire 1 1 reset $end
$var wire 1 6 set_alarm $end
$var wire 1 7 set_timer $end
$var wire 4 L timer_minutes [3:0] $end
$var wire 12 M year [11:0] $end
$var wire 6 N timer_sec_left [5:0] $end
$var wire 6 O timer_min_left [5:0] $end
$var wire 1 $ timer_buzzer $end
$var wire 6 P sec [5:0] $end
$var wire 4 Q month [3:0] $end
$var wire 6 R min [5:0] $end
$var wire 6 S hr [5:0] $end
$var wire 5 T day [4:0] $end
$var wire 1 * alarm_buzzer $end
$var wire 1 + AM_PM $end
$scope module am $end
$var wire 6 U alarm_hr [5:0] $end
$var wire 6 V alarm_min [5:0] $end
$var wire 1 / clk $end
$var wire 1 1 reset $end
$var wire 1 6 set_alarm $end
$var wire 6 W curr_sec [5:0] $end
$var wire 6 X curr_min [5:0] $end
$var wire 6 Y curr_hr [5:0] $end
$var reg 1 * alarm_buzzer $end
$var reg 6 Z alarm_hr_reg [5:0] $end
$var reg 6 [ alarm_min_reg [5:0] $end
$upscope $end
$scope module tk $end
$var wire 1 , AM_mode $end
$var wire 1 = add_hour $end
$var wire 1 < add_minute $end
$var wire 1 / clk $end
$var wire 1 1 reset $end
$var reg 1 + AM_PM $end
$var reg 1 \ AM_PM_next $end
$var reg 1 ] AM_mode_prev $end
$var reg 5 ^ day [4:0] $end
$var reg 5 _ day_next [4:0] $end
$var reg 6 ` days_in_month [5:0] $end
$var reg 6 a hr [5:0] $end
$var reg 6 b hr_next [5:0] $end
$var reg 6 c min [5:0] $end
$var reg 6 d min_next [5:0] $end
$var reg 4 e month [3:0] $end
$var reg 4 f month_next [3:0] $end
$var reg 2 g next_state [1:0] $end
$var reg 6 h sec [5:0] $end
$var reg 6 i sec_next [5:0] $end
$var reg 2 j state [1:0] $end
$var reg 12 k year [11:0] $end
$var reg 12 l year_next [11:0] $end
$upscope $end
$scope module tm $end
$var wire 1 / clk $end
$var wire 1 1 reset $end
$var wire 1 7 set_timer $end
$var wire 4 m timer_minutes [3:0] $end
$var wire 6 n timer_sec_left [5:0] $end
$var wire 6 o timer_min_left [5:0] $end
$var reg 1 $ timer_buzzer $end
$var reg 10 p timer_sec_total [9:0] $end
$upscope $end
$upscope $end
$upscope $end
$upscope $end
$enddefinitions $end
#0
$dumpvars
b0 p
b0 o
b0 n
b0 m
b11111100100 l
b11111100100 k
b0 j
b1 i
b0 h
b0 g
b1 f
b1 e
b0 d
b0 c
b1100 b
b1100 a
bx `
b1 _
b1 ^
1]
0\
b0 [
b0 Z
b1100 Y
b0 X
b0 W
b0 V
b0 U
b1 T
b1100 S
b0 R
b1 Q
b0 P
b0 O
b0 N
b11111100100 M
b0 L
b0 K
b0 J
b0 I
b0 H
b0 G
b0 F
b0 E
0D
b1 C
b1100 B
1A
b0 @
b1 ?
b0 >
0=
0<
b0 ;
0:
b0 9
b11111100100 8
07
06
b101 5
bx 4
03
02
11
00
0/
0.
0-
1,
0+
0*
b1 )
b1100 (
b0 '
b1 &
b0 %
0$
b0 #
b0 "
b11111100100 !
$end
#500
1/
#1000
0/
#1500
1/
#2000
0/
01
#2500
b10 i
b1 %
b1 >
b1 P
b1 W
b1 h
1/
#3000
0/
#3500
b11 i
b10 %
b10 >
b10 P
b10 W
b10 h
1/
#4000
0/
#4500
b100 i
b11 %
b11 >
b11 P
b11 W
b11 h
1/
#5000
0/
#5500
b101 i
b100 %
b100 >
b100 P
b100 W
b100 h
1/
#6000
0/
#6500
b110 i
b101 %
b101 >
b101 P
b101 W
b101 h
1/
#7000
b1 G
0/
10
#7500
b111 i
b10 G
b110 %
b110 >
b110 P
b110 W
b110 h
0A
1:
b1 H
1/
#8000
b1 G
0/
b0 4
00
#8500
b1000 i
b111 %
b111 >
b111 P
b111 W
b111 h
1/
#9000
0/
#9500
b1001 i
b1000 %
b1000 >
b1000 P
b1000 W
b1000 h
1/
#10000
0/
#10500
b1010 i
b1001 %
b1001 >
b1001 P
b1001 W
b1001 h
1/
#11000
0/
#11500
b1011 i
b1010 %
b1010 >
b1010 P
b1010 W
b1010 h
1/
#12000
0/
#12500
b1100 i
b1011 %
b1011 >
b1011 P
b1011 W
b1011 h
1/
#13000
0/
1.
#13500
b1101 i
b1100 %
b1100 >
b1100 P
b1100 W
b1100 h
b1 I
b1 L
b1 m
1/
#14000
0/
b1 4
0.
#14500
b1110 i
b1101 %
b1101 >
b1101 P
b1101 W
b1101 h
1/
#15000
0/
#15500
b1111 i
b1110 %
b1110 >
b1110 P
b1110 W
b1110 h
1/
#16000
0/
#16500
b10000 i
b1111 %
b1111 >
b1111 P
b1111 W
b1111 h
1/
#17000
0/
#17500
b10001 i
b10000 %
b10000 >
b10000 P
b10000 W
b10000 h
1/
#18000
0/
#18500
b10010 i
b10001 %
b10001 >
b10001 P
b10001 W
b10001 h
1/
#19000
0/
1.
#19500
b10011 i
b10010 %
b10010 >
b10010 P
b10010 W
b10010 h
b10 I
b10 L
b10 m
1/
#20000
0/
b10 4
0.
#20500
b10100 i
b10011 %
b10011 >
b10011 P
b10011 W
b10011 h
1/
#21000
0/
#21500
b10101 i
b10100 %
b10100 >
b10100 P
b10100 W
b10100 h
1/
#22000
0/
#22500
b10110 i
b10101 %
b10101 >
b10101 P
b10101 W
b10101 h
1/
#23000
0/
#23500
b10111 i
b10110 %
b10110 >
b10110 P
b10110 W
b10110 h
1/
#24000
0/
#24500
b11000 i
b10111 %
b10111 >
b10111 P
b10111 W
b10111 h
1/
#25000
0/
1.
#25500
b11001 i
b11000 %
b11000 >
b11000 P
b11000 W
b11000 h
b11 I
b11 L
b11 m
1/
#26000
0/
b11 4
0.
#26500
b11010 i
b11001 %
b11001 >
b11001 P
b11001 W
b11001 h
1/
#27000
0/
#27500
b11011 i
b11010 %
b11010 >
b11010 P
b11010 W
b11010 h
1/
#28000
0/
#28500
b11100 i
b11011 %
b11011 >
b11011 P
b11011 W
b11011 h
1/
#29000
0/
#29500
b11101 i
b11100 %
b11100 >
b11100 P
b11100 W
b11100 h
1/
#30000
0/
#30500
b11110 i
b11101 %
b11101 >
b11101 P
b11101 W
b11101 h
1/
#31000
0/
1.
#31500
b11111 i
b11110 %
b11110 >
b11110 P
b11110 W
b11110 h
b100 I
b100 L
b100 m
1/
#32000
0/
b100 4
0.
#32500
b100000 i
b11111 %
b11111 >
b11111 P
b11111 W
b11111 h
1/
#33000
0/
#33500
b100001 i
b100000 %
b100000 >
b100000 P
b100000 W
b100000 h
1/
#34000
0/
#34500
b100010 i
b100001 %
b100001 >
b100001 P
b100001 W
b100001 h
1/
#35000
0/
#35500
b100011 i
b100010 %
b100010 >
b100010 P
b100010 W
b100010 h
1/
#36000
0/
#36500
b100100 i
b100011 %
b100011 >
b100011 P
b100011 W
b100011 h
1/
#37000
0/
1.
#37500
b100101 i
b100100 %
b100100 >
b100100 P
b100100 W
b100100 h
b101 I
b101 L
b101 m
1/
#38000
0/
b101 4
0.
#38500
b100110 i
b100101 %
b100101 >
b100101 P
b100101 W
b100101 h
1/
#39000
0/
#39500
b100111 i
b100110 %
b100110 >
b100110 P
b100110 W
b100110 h
1/
#40000
0/
#40500
b101000 i
b100111 %
b100111 >
b100111 P
b100111 W
b100111 h
1/
#41000
0/
#41500
b101001 i
b101000 %
b101000 >
b101000 P
b101000 W
b101000 h
1/
#42000
0/
#42500
b101010 i
b101001 %
b101001 >
b101001 P
b101001 W
b101001 h
1/
#43000
17
0/
13
#43500
b101011 i
b101 #
b101 ;
b101 O
b101 o
b101010 %
b101010 >
b101010 P
b101010 W
b101010 h
b100101100 p
1/
#44000
07
0/
03
#44500
b100 #
b100 ;
b100 O
b100 o
b111011 "
b111011 9
b111011 N
b111011 n
b101100 i
b100101011 p
b101011 %
b101011 >
b101011 P
b101011 W
b101011 h
1/
#45000
0/
#45500
b101101 i
b111010 "
b111010 9
b111010 N
b111010 n
b101100 %
b101100 >
b101100 P
b101100 W
b101100 h
b100101010 p
1/
#46000
0/
#46500
b111001 "
b111001 9
b111001 N
b111001 n
b101110 i
b100101001 p
b101101 %
b101101 >
b101101 P
b101101 W
b101101 h
1/
#47000
0/
#47500
b101111 i
b111000 "
b111000 9
b111000 N
b111000 n
b101110 %
b101110 >
b101110 P
b101110 W
b101110 h
b100101000 p
1/
#48000
0/
#48500
b110111 "
b110111 9
b110111 N
b110111 n
b110000 i
b100100111 p
b101111 %
b101111 >
b101111 P
b101111 W
b101111 h
1/
#49000
0/
#49500
b110001 i
b110110 "
b110110 9
b110110 N
b110110 n
b110000 %
b110000 >
b110000 P
b110000 W
b110000 h
b100100110 p
1/
#50000
0/
#50500
b110101 "
b110101 9
b110101 N
b110101 n
b110010 i
b100100101 p
b110001 %
b110001 >
b110001 P
b110001 W
b110001 h
1/
#51000
0/
#51500
b110011 i
b110100 "
b110100 9
b110100 N
b110100 n
b110010 %
b110010 >
b110010 P
b110010 W
b110010 h
b100100100 p
1/
#52000
0/
#52500
b110011 "
b110011 9
b110011 N
b110011 n
b110100 i
b100100011 p
b110011 %
b110011 >
b110011 P
b110011 W
b110011 h
1/
#53000
0/
#53500
b110101 i
b110010 "
b110010 9
b110010 N
b110010 n
b110100 %
b110100 >
b110100 P
b110100 W
b110100 h
b100100010 p
1/
#54000
0/
#54500
b110001 "
b110001 9
b110001 N
b110001 n
b110110 i
b100100001 p
b110101 %
b110101 >
b110101 P
b110101 W
b110101 h
1/
#55000
0/
#55500
b110111 i
b110000 "
b110000 9
b110000 N
b110000 n
b110110 %
b110110 >
b110110 P
b110110 W
b110110 h
b100100000 p
1/
#56000
0/
#56500
b101111 "
b101111 9
b101111 N
b101111 n
b111000 i
b100011111 p
b110111 %
b110111 >
b110111 P
b110111 W
b110111 h
1/
#57000
0/
#57500
b111001 i
b101110 "
b101110 9
b101110 N
b101110 n
b111000 %
b111000 >
b111000 P
b111000 W
b111000 h
b100011110 p
1/
#58000
0/
#58500
b101101 "
b101101 9
b101101 N
b101101 n
b111010 i
b100011101 p
b111001 %
b111001 >
b111001 P
b111001 W
b111001 h
1/
#59000
0/
#59500
b111011 i
b101100 "
b101100 9
b101100 N
b101100 n
b111010 %
b111010 >
b111010 P
b111010 W
b111010 h
b100011100 p
1/
#60000
0/
#60500
b101011 "
b101011 9
b101011 N
b101011 n
b1 g
b0 i
b100011011 p
b111011 %
b111011 >
b111011 P
b111011 W
b111011 h
1/
#61000
0/
#61500
b0 g
b1 d
b101010 "
b101010 9
b101010 N
b101010 n
b0 %
b0 >
b0 P
b0 W
b0 h
b1 j
b100011010 p
1/
#62000
0/
#62500
b101001 "
b101001 9
b101001 N
b101001 n
b1 i
b100011001 p
b1 '
b1 @
b1 R
b1 X
b1 c
b0 j
1/
#63000
0/
#63500
b10 i
b101000 "
b101000 9
b101000 N
b101000 n
b1 %
b1 >
b1 P
b1 W
b1 h
b100011000 p
1/
#64000
0/
#64500
b100111 "
b100111 9
b100111 N
b100111 n
b11 i
b100010111 p
b10 %
b10 >
b10 P
b10 W
b10 h
1/
#65000
0/
#65500
b100 i
b100110 "
b100110 9
b100110 N
b100110 n
b11 %
b11 >
b11 P
b11 W
b11 h
b100010110 p
1/
#66000
0/
#66500
b100101 "
b100101 9
b100101 N
b100101 n
b101 i
b100010101 p
b100 %
b100 >
b100 P
b100 W
b100 h
1/
#67000
0/
#67500
b110 i
b100100 "
b100100 9
b100100 N
b100100 n
b101 %
b101 >
b101 P
b101 W
b101 h
b100010100 p
1/
#68000
0/
#68500
b100011 "
b100011 9
b100011 N
b100011 n
b111 i
b100010011 p
b110 %
b110 >
b110 P
b110 W
b110 h
1/
#69000
0/
#69500
b1000 i
b100010 "
b100010 9
b100010 N
b100010 n
b111 %
b111 >
b111 P
b111 W
b111 h
b100010010 p
1/
#70000
0/
#70500
b100001 "
b100001 9
b100001 N
b100001 n
b1001 i
b100010001 p
b1000 %
b1000 >
b1000 P
b1000 W
b1000 h
1/
#71000
0/
#71500
b1010 i
b100000 "
b100000 9
b100000 N
b100000 n
b1001 %
b1001 >
b1001 P
b1001 W
b1001 h
b100010000 p
1/
#72000
0/
#72500
b11111 "
b11111 9
b11111 N
b11111 n
b1011 i
b100001111 p
b1010 %
b1010 >
b1010 P
b1010 W
b1010 h
1/
#73000
0/
#73500
b1100 i
b11110 "
b11110 9
b11110 N
b11110 n
b1011 %
b1011 >
b1011 P
b1011 W
b1011 h
b100001110 p
1/
#74000
0/
#74500
b11101 "
b11101 9
b11101 N
b11101 n
b1101 i
b100001101 p
b1100 %
b1100 >
b1100 P
b1100 W
b1100 h
1/
#75000
0/
#75500
b1110 i
b11100 "
b11100 9
b11100 N
b11100 n
b1101 %
b1101 >
b1101 P
b1101 W
b1101 h
b100001100 p
1/
#76000
0/
#76500
b11011 "
b11011 9
b11011 N
b11011 n
b1111 i
b100001011 p
b1110 %
b1110 >
b1110 P
b1110 W
b1110 h
1/
#77000
0/
#77500
b10000 i
b11010 "
b11010 9
b11010 N
b11010 n
b1111 %
b1111 >
b1111 P
b1111 W
b1111 h
b100001010 p
1/
#78000
0/
#78500
b11001 "
b11001 9
b11001 N
b11001 n
b10001 i
b100001001 p
b10000 %
b10000 >
b10000 P
b10000 W
b10000 h
1/
#79000
0/
#79500
b10010 i
b11000 "
b11000 9
b11000 N
b11000 n
b10001 %
b10001 >
b10001 P
b10001 W
b10001 h
b100001000 p
1/
#80000
0/
#80500
b10111 "
b10111 9
b10111 N
b10111 n
b10011 i
b100000111 p
b10010 %
b10010 >
b10010 P
b10010 W
b10010 h
1/
#81000
0/
#81500
b10100 i
b10110 "
b10110 9
b10110 N
b10110 n
b10011 %
b10011 >
b10011 P
b10011 W
b10011 h
b100000110 p
1/
#82000
0/
#82500
b10101 "
b10101 9
b10101 N
b10101 n
b10101 i
b100000101 p
b10100 %
b10100 >
b10100 P
b10100 W
b10100 h
1/
#83000
0/
#83500
b10110 i
b10100 "
b10100 9
b10100 N
b10100 n
b10101 %
b10101 >
b10101 P
b10101 W
b10101 h
b100000100 p
1/
#84000
0/
#84500
b10011 "
b10011 9
b10011 N
b10011 n
b10111 i
b100000011 p
b10110 %
b10110 >
b10110 P
b10110 W
b10110 h
1/
#85000
0/
#85500
b11000 i
b10010 "
b10010 9
b10010 N
b10010 n
b10111 %
b10111 >
b10111 P
b10111 W
b10111 h
b100000010 p
1/
#86000
0/
#86500
b10001 "
b10001 9
b10001 N
b10001 n
b11001 i
b100000001 p
b11000 %
b11000 >
b11000 P
b11000 W
b11000 h
1/
#87000
0/
#87500
b11010 i
b10000 "
b10000 9
b10000 N
b10000 n
b11001 %
b11001 >
b11001 P
b11001 W
b11001 h
b100000000 p
1/
#88000
0/
#88500
b1111 "
b1111 9
b1111 N
b1111 n
b11011 i
b11111111 p
b11010 %
b11010 >
b11010 P
b11010 W
b11010 h
1/
#89000
0/
#89500
b11100 i
b1110 "
b1110 9
b1110 N
b1110 n
b11011 %
b11011 >
b11011 P
b11011 W
b11011 h
b11111110 p
1/
#90000
0/
#90500
b1101 "
b1101 9
b1101 N
b1101 n
b11101 i
b11111101 p
b11100 %
b11100 >
b11100 P
b11100 W
b11100 h
1/
#91000
0/
#91500
b11110 i
b1100 "
b1100 9
b1100 N
b1100 n
b11101 %
b11101 >
b11101 P
b11101 W
b11101 h
b11111100 p
1/
#92000
0/
#92500
b1011 "
b1011 9
b1011 N
b1011 n
b11111 i
b11111011 p
b11110 %
b11110 >
b11110 P
b11110 W
b11110 h
1/
#93000
0/
#93500
b100000 i
b1010 "
b1010 9
b1010 N
b1010 n
b11111 %
b11111 >
b11111 P
b11111 W
b11111 h
b11111010 p
1/
#94000
0/
