Clock/codes/clock2.v
`timescale 1s / 1ms

module timekeeper(
    input             clk,
    input             reset,
    input             AM_mode,
    input             add_hour,
    input             add_minute,
    output reg [5:0]  sec,
    output reg [5:0]  min,
    output reg [5:0]  hr,
    output reg        AM_PM,
    output reg [4:0]  day,
    output reg [3:0]  month,
    output reg [11:0] year
);

  // State encoding
  localparam S_SEC  = 2'd0,
             S_MIN  = 2'd1,
             S_HR   = 2'd2,
             S_DATE = 2'd3;

  // State registers
  reg [1:0] state, next_state;

  // Next value registers
  reg [5:0] sec_next, min_next, hr_next;
  reg       AM_PM_next;
  reg [4:0] day_next;
  reg [3:0] month_next;
  reg [11:0] year_next;
  reg [5:0] days_in_month;

  // Track AM_mode changes
  reg AM_mode_prev;

  // Sequential logic
  always @(posedge clk or posedge reset) begin
    if (reset) begin
      state        <= S_SEC;
      sec          <= 0;
      min          <= 0;
      hr           <= 12;
      AM_PM        <= 0;
      day          <= 1;
      month        <= 1;
      year         <= 2020;
      AM_mode_prev <= AM_mode;
    end else begin
      state        <= next_state;
      sec          <= sec_next;
      min          <= min_next;
      hr           <= hr_next;
      AM_PM        <= AM_PM_next;
      day          <= day_next;
      month        <= month_next;
      year         <= year_next;
      AM_mode_prev <= AM_mode; // Track previous AM_mode
    end
  end

  // Combinational logic
  always @(*) begin
    // Default holds
    next_state   = state;
    sec_next     = sec;
    min_next     = min;
    hr_next      = hr;
    AM_PM_next   = AM_PM;
    day_next     = day;
    month_next   = month;
    year_next    = year;

    // Handle mode change (24h <-> 12h)
    if (AM_mode != AM_mode_prev) begin
      if (AM_mode) begin
        // 24h -> 12h
        if (hr == 0) begin
          hr_next = 12;
          AM_PM_next = 0;
        end else if (hr == 12) begin
          hr_next = 12;
          AM_PM_next = 1;
        end else if (hr > 12) begin
          hr_next = hr - 12;
          AM_PM_next = 1;
        end else begin
          hr_next = hr;
          AM_PM_next = 0;
        end
      end else begin
        // 12h -> 24h
        if (hr == 12 && AM_PM == 0)
          hr_next = 0;
        else if (hr == 12 && AM_PM == 1)
          hr_next = 12;
        else if (AM_PM == 1)
          hr_next = hr + 12;
        else
          hr_next = hr;
      end
    end

    // Main FSM
    case (state)
      S_SEC: begin
        if (sec == 6'd59) begin
          sec_next   = 0;
          next_state = S_MIN;
        end else begin
          sec_next   = sec + 1;
          next_state = S_SEC;
        end
      end

      S_MIN: begin
        if (min == 6'd59) begin
          min_next   = 0;
          next_state = S_HR;
        end else begin
          min_next   = min + 1;
          next_state = S_SEC;
        end
      end

      S_HR: begin
        if (AM_mode) begin
          if (hr == 6'd11) begin
            hr_next    = 12;
            AM_PM_next = ~AM_PM;
          end else if (hr == 6'd12) begin
            hr_next = 1;
          end else begin
            hr_next = hr + 1;
          end
        end else begin
          if (hr == 6'd23)
            hr_next = 0;
          else
            hr_next = hr + 1;
        end
        next_state = S_DATE;
      end

      S_DATE: begin
        if ((AM_mode && hr_next == 12 && AM_PM_next == 0) ||
            (!AM_mode && hr_next == 0)) begin

          // Get correct days in current month
          case (month)
            1, 3, 5, 7, 8, 10, 12: days_in_month = 31;
            4, 6, 9, 11:           days_in_month = 30;
            2: begin
              if ((year % 4 == 0 && year % 100 != 0) || (year % 400 == 0))
                days_in_month = 29;
              else
                days_in_month = 28;
            end
            default: days_in_month = 31;
          endcase

          if (day == 5'd30 && month == 4'd4 && year == 12'd2025) begin
            day_next   = 1;
            month_next = 1;
            year_next  = 2020;
          end else begin
            if (day == days_in_month) begin
              day_next = 1;
              if (month == 4'd12) begin
                month_next = 1;
                year_next  = year + 1;
              end else begin
                month_next = month + 1;
              end
            end else begin
              day_next = day + 1;
            end
          end
        end
        next_state = S_SEC;
      end
    endcase

    // Manual add minute
    if (add_minute) begin
      if (min == 6'd59) begin
        min_next = 0;
        if (AM_mode) begin
          if (hr == 6'd11) begin
            hr_next    = 12;
            AM_PM_next = ~AM_PM;
          end else if (hr == 6'd12) begin
            hr_next = 1;
          end else begin
            hr_next = hr + 1;
          end
        end else begin
          if (hr == 6'd23)
            hr_next = 0;
          else
            hr_next = hr + 1;
        end
      end else begin
        min_next = min + 1;
      end
    end

    // Manual add hour
    if (add_hour) begin
      if (AM_mode) begin
        if (hr == 6'd11) begin
          hr_next    = 12;
          AM_PM_next = ~AM_PM;
        end else if (hr == 6'd12) begin
          hr_next = 1;
        end else begin
          hr_next = hr + 1;
        end
      end else begin
        if (hr == 6'd23)
          hr_next = 0;
        else
          hr_next = hr + 1;
      end
    end
  end

endmodule


module timer_module(
    input         clk,
    input         reset,
    input         set_timer,
    input  [3:0]  timer_minutes,
    output reg    timer_buzzer,
    output [5:0]  timer_min_left,
    output [5:0]  timer_sec_left
);
  reg [9:0] timer_sec_total;
  assign timer_min_left = timer_sec_total / 60;
  assign timer_sec_left = timer_sec_total % 60;

  always @(posedge clk or posedge reset) begin
    if (reset) begin
      timer_sec_total <= 0;
      timer_buzzer    <= 0;
    end else begin
      if (set_timer && timer_sec_total == 0)
        timer_sec_total <= timer_minutes * 60;
      else if (timer_sec_total > 0) begin
        timer_sec_total <= timer_sec_total - 1;
        timer_buzzer    <= (timer_sec_total == 1);
      end else
        timer_buzzer    <= 0;
    end
  end
endmodule



module alarm_module(
    input         clk,
    input         reset,
    input         set_alarm,
    input  [5:0]  alarm_hr,
    input  [5:0]  alarm_min,
    input  [5:0]  curr_hr,
    input  [5:0]  curr_min,
    input  [5:0]  curr_sec,
    output reg    alarm_buzzer
);
  reg [5:0] alarm_hr_reg, alarm_min_reg;

  always @(posedge clk or posedge reset) begin
    if (reset) begin
      alarm_hr_reg  <= 0;
      alarm_min_reg <= 0;
      alarm_buzzer  <= 0;
    end else begin
      if (set_alarm) begin
        alarm_hr_reg  <= alarm_hr;
        alarm_min_reg <= alarm_min;
      end
      alarm_buzzer <= (curr_hr == alarm_hr_reg &&
                       curr_min == alarm_min_reg &&
                       curr_sec == 0);
    end
  end
endmodule


module digital_clock(
    input         clk,
    input         reset,
    input         AM_mode,
    input         set_timer,
    input  [3:0]  timer_minutes,
    input         add_hour,
    input         add_minute,
    input         set_alarm,
    input  [5:0]  alarm_hr,
    input  [5:0]  alarm_min,
    output [5:0]  sec,
    output [5:0]  min,
    output [5:0]  hr,
    output        AM_PM,
    output [4:0]  day,
    output [3:0]  month,
    output [11:0] year,
    output        timer_buzzer,
    output        alarm_buzzer,
    output [5:0]  timer_min_left,
    output [5:0]  timer_sec_left
);
  timekeeper   tk(clk, reset, AM_mode, add_hour, add_minute,
                  sec, min, hr, AM_PM, day, month, year);

  timer_module tm(clk, reset, set_timer, timer_minutes,
                  timer_buzzer, timer_min_left, timer_sec_left);

  alarm_module am(clk, reset, set_alarm,
                  alarm_hr, alarm_min,
                  hr, min, sec,
                  alarm_buzzer);
endmodule



module clock_with_mode_fsm(
    input        clk,
    input        reset,
    input        mode_btn,
    input        add_hour,
    input        add_minute,
    input        set_timer_btn,
    input        set_alarm_btn,
    input        AM_mode,
    output [5:0] sec,
    output [5:0] min,
    output [5:0] hr,
    output       AM_PM,
    output [4:0] day,
    output [3:0] month,
    output [11:0] year,
    output       timer_buzzer,
    output       alarm_buzzer,
    output [5:0] timer_min_left,
    output [5:0] timer_sec_left
);

  // FSM states
  localparam IDLE      = 2'd0,
             SET_TIMER = 2'd1,
             SET_ALARM = 2'd2;

  reg [1:0] state, next_state;

  // State register
  always @(posedge clk or posedge reset) begin
    if (reset) state <= IDLE;
    else       state <= next_state;
  end

  // Next-state logic
  always @(*) begin
    next_state = state;
    case(state)
      IDLE:      if (mode_btn) next_state = SET_TIMER;
      SET_TIMER: if (mode_btn) next_state = SET_ALARM;
      SET_ALARM: if (mode_btn) next_state = IDLE;
    endcase
  end
  wire idle_mode_active  = (state == IDLE);   
  wire timer_mode_active = (state == SET_TIMER);
  wire alarm_mode_active = (state == SET_ALARM);

  // Adjust timer_minutes in SET_TIMER
  reg [3:0] timer_minutes;
  always @(posedge clk or posedge reset) begin
    if (reset)                              timer_minutes <= 4'd0;
    else if (timer_mode_active && add_minute) timer_minutes <= timer_minutes + 1;
    else if (timer_mode_active && add_hour)   timer_minutes <= timer_minutes + 4;
  end

  // Adjust alarm_hr/min in SET_ALARM
  reg [5:0] alarm_hr, alarm_min;
  always @(posedge clk or posedge reset) begin
    if (reset) begin
      alarm_hr  <= 6'd0;
      alarm_min <= 6'd0;
    end else if (alarm_mode_active && add_hour) begin
      alarm_hr <= (alarm_hr == (AM_mode ? 12 : 23)) ? 0 : alarm_hr + 1;
    end else if (alarm_mode_active && add_minute) begin
      alarm_min <= (alarm_min == 6'd59) ? 0 : alarm_min + 1;
    end
  end

  wire set_timer = timer_mode_active & set_timer_btn;
  wire set_alarm = alarm_mode_active & set_alarm_btn;
  wire time_add_hour=idle_mode_active?add_hour:1'b0;
  wire time_add_minute=idle_mode_active?add_minute:1'b0;
  digital_clock UDC (
    .clk(clk), .reset(reset), .AM_mode(AM_mode),
    .set_timer(set_timer),     .timer_minutes(timer_minutes),
    .add_hour(time_add_hour),           .add_minute(time_add_minute),
    .set_alarm(set_alarm),
    .alarm_hr(alarm_hr),       .alarm_min(alarm_min),
    .sec(sec), .min(min), .hr(hr), .AM_PM(AM_PM),
    .day(day), .month(month), .year(year),
    .timer_buzzer(timer_buzzer),
    .alarm_buzzer(alarm_buzzer),
    .timer_min_left(timer_min_left),
    .timer_sec_left(timer_sec_left)
  );

endmodule

Clock/codes/disptest.v
`timescale 1s / 1ms

module test;
  reg        clk, reset;
  reg        mode_btn, add_hour, add_minute;
  reg        set_timer_btn, set_alarm_btn;
  reg        AM_mode;
  wire [5:0] sec, min, hr, timer_min_left, timer_sec_left;
  wire       AM_PM, timer_buzzer, alarm_buzzer;
  wire [4:0] day;
  wire [3:0] month;
  wire [11:0] year;

  clock_with_mode_fsm uut(
    .clk(clk), .reset(reset),
    .mode_btn(mode_btn),
    .add_hour(add_hour), .add_minute(add_minute),
    .set_timer_btn(set_timer_btn),
    .set_alarm_btn(set_alarm_btn),
    .AM_mode(AM_mode),
    .sec(sec), .min(min), .hr(hr), .AM_PM(AM_PM),
    .day(day), .month(month), .year(year),
    .timer_buzzer(timer_buzzer),
    .alarm_buzzer(alarm_buzzer),
    .timer_min_left(timer_min_left),
    .timer_sec_left(timer_sec_left)
  );
integer i;
  initial begin
    // dump waves
    $dumpfile("disptest.vcd");
    $dumpvars(0,test);

    // initialize
    clk            = 0;
    reset          = 1;
    AM_mode        = 1;
    mode_btn       = 0;
    add_hour       = 0;
    add_minute     = 0;
    set_timer_btn  = 0;
    set_alarm_btn  = 0;
    #1 reset = 0;

    for (i = 0; i < 22; i = i + 1) begin
    #1 add_hour = 1; 
    #1 add_hour = 0;  // +1 hour
    #1 add_minute = 1; 
    #1 add_minute = 0;  // +1 minute
  end
  for (i = 0; i < 35; i = i + 1) begin
    #1 add_minute = 1; 
    #1 add_minute = 0;  // +1 minute
  end
  #23;
  AM_mode=0;
  for (i = 0; i < 25; i = i + 1) begin
    #1 add_hour = 1; 
    #1 add_hour = 0;  // +1 hour
    #1 add_minute = 1; 
    #1 add_minute = 0;  // +1 minute
  end
  for (i = 0; i < 35; i = i + 1) begin
    #1 add_minute = 1; 
    #1 add_minute = 0;  // +1 minute
  end
  #23;
    $finish;
  end

  // 0.5s clock
  always #0.5 clk = ~clk;

  // display
  always @(posedge clk) begin
    $display("AM_MODE=%b |MODE=%0d | %02d:%02d:%02d %s | %02d/%02d/%04d | Tleft=%02d:%02d Bz=%b | Albz=%b",AM_mode,
      uut.state,
      hr, min, sec, AM_mode?(AM_PM ? "PM" : "AM"):"HOURS",
      day, month, year,
      timer_min_left, timer_sec_left, timer_buzzer,
      alarm_buzzer
    );
  end

endmodule

Clock/codes/disptest.vcd
$date
	Wed May  7 00:32:23 2025
$end
$version
	Icarus Verilog
$end
$timescale
	1ms
$end
$scope module test $end
$var wire 12 ! year [11:0] $end
$var wire 6 " timer_sec_left [5:0] $end
$var wire 6 # timer_min_left [5:0] $end
$var wire 1 $ timer_buzzer $end
$var wire 6 % sec [5:0] $end
$var wire 4 & month [3:0] $end
$var wire 6 ' min [5:0] $end
$var wire 6 ( hr [5:0] $end
$var wire 5 ) day [4:0] $end
$var wire 1 * alarm_buzzer $end
$var wire 1 + AM_PM $end
$var reg 1 , AM_mode $end
$var reg 1 - add_hour $end
$var reg 1 . add_minute $end
$var reg 1 / clk $end
$var reg 1 0 mode_btn $end
$var reg 1 1 reset $end
$var reg 1 2 set_alarm_btn $end
$var reg 1 3 set_timer_btn $end
$var integer 32 4 i [31:0] $end
$scope module uut $end
$var wire 1 , AM_mode $end
$var wire 1 - add_hour $end
$var wire 1 . add_minute $end
$var wire 1 / clk $end
$var wire 1 0 mode_btn $end
$var wire 1 1 reset $end
$var wire 1 5 set_alarm $end
$var wire 1 2 set_alarm_btn $end
$var wire 1 6 set_timer $end
$var wire 1 3 set_timer_btn $end
$var wire 12 7 year [11:0] $end
$var wire 6 8 timer_sec_left [5:0] $end
$var wire 1 9 timer_mode_active $end
$var wire 6 : timer_min_left [5:0] $end
$var wire 1 $ timer_buzzer $end
$var wire 1 ; time_add_minute $end
$var wire 1 < time_add_hour $end
$var wire 6 = sec [5:0] $end
$var wire 4 > month [3:0] $end
$var wire 6 ? min [5:0] $end
$var wire 1 @ idle_mode_active $end
$var wire 6 A hr [5:0] $end
$var wire 5 B day [4:0] $end
$var wire 1 C alarm_mode_active $end
$var wire 1 * alarm_buzzer $end
$var wire 1 + AM_PM $end
$var reg 6 D alarm_hr [5:0] $end
$var reg 6 E alarm_min [5:0] $end
$var reg 2 F next_state [1:0] $end
$var reg 2 G state [1:0] $end
$var reg 4 H timer_minutes [3:0] $end
$scope module UDC $end
$var wire 1 , AM_mode $end
$var wire 1 < add_hour $end
$var wire 1 ; add_minute $end
$var wire 6 I alarm_hr [5:0] $end
$var wire 6 J alarm_min [5:0] $end
$var wire 1 / clk $end
$var wire 1 1 reset $end
$var wire 1 5 set_alarm $end
$var wire 1 6 set_timer $end
$var wire 4 K timer_minutes [3:0] $end
$var wire 12 L year [11:0] $end
$var wire 6 M timer_sec_left [5:0] $end
$var wire 6 N timer_min_left [5:0] $end
$var wire 1 $ timer_buzzer $end
$var wire 6 O sec [5:0] $end
$var wire 4 P month [3:0] $end
$var wire 6 Q min [5:0] $end
$var wire 6 R hr [5:0] $end
$var wire 5 S day [4:0] $end
$var wire 1 * alarm_buzzer $end
$var wire 1 + AM_PM $end
$scope module am $end
$var wire 6 T alarm_hr [5:0] $end
$var wire 6 U alarm_min [5:0] $end
$var wire 1 / clk $end
$var wire 1 1 reset $end
$var wire 1 5 set_alarm $end
$var wire 6 V curr_sec [5:0] $end
$var wire 6 W curr_min [5:0] $end
$var wire 6 X curr_hr [5:0] $end
$var reg 1 * alarm_buzzer $end
$var reg 6 Y alarm_hr_reg [5:0] $end
$var reg 6 Z alarm_min_reg [5:0] $end
$upscope $end
$scope module tk $end
$var wire 1 , AM_mode $end
$var wire 1 < add_hour $end
$var wire 1 ; add_minute $end
$var wire 1 / clk $end
$var wire 1 1 reset $end
$var reg 1 + AM_PM $end
$var reg 1 [ AM_PM_next $end
$var reg 1 \ AM_mode_prev $end
$var reg 5 ] day [4:0] $end
$var reg 5 ^ day_next [4:0] $end
$var reg 6 _ days_in_month [5:0] $end
$var reg 6 ` hr [5:0] $end
$var reg 6 a hr_next [5:0] $end
$var reg 6 b min [5:0] $end
$var reg 6 c min_next [5:0] $end
$var reg 4 d month [3:0] $end
$var reg 4 e month_next [3:0] $end
$var reg 2 f next_state [1:0] $end
$var reg 6 g sec [5:0] $end
$var reg 6 h sec_next [5:0] $end
$var reg 2 i state [1:0] $end
$var reg 12 j year [11:0] $end
$var reg 12 k year_next [11:0] $end
$upscope $end
$scope module tm $end
$var wire 1 / clk $end
$var wire 1 1 reset $end
$var wire 1 6 set_timer $end
$var wire 4 l timer_minutes [3:0] $end
$var wire 6 m timer_sec_left [5:0] $end
$var wire 6 n timer_min_left [5:0] $end
$var reg 1 $ timer_buzzer $end
$var reg 10 o timer_sec_total [9:0] $end
$upscope $end
$upscope $end
$upscope $end
$upscope $end
$enddefinitions $end
#0
$dumpvars
b0 o
b0 n
b0 m
b0 l
b11111100100 k
b11111100100 j
b0 i
b1 h
b0 g
b0 f
b1 e
b1 d
b0 c
b0 b
b1100 a
b1100 `
bx _
b1 ^
b1 ]
1\
0[
b0 Z
b0 Y
b1100 X
b0 W
b0 V
b0 U
b0 T
b1 S
b1100 R
b0 Q
b1 P
b0 O
b0 N
b0 M
b11111100100 L
b0 K
b0 J
b0 I
b0 H
b0 G
b0 F
b0 E
b0 D
0C
b1 B
b1100 A
1@
b0 ?
b1 >
b0 =
0<
0;
b0 :
09
b0 8
b11111100100 7
06
05
bx 4
03
02
11
00
0/
0.
0-
1,
0+
0*
b1 )
b1100 (
b0 '
b1 &
b0 %
0$
b0 #
b0 "
b11111100100 !
$end
#500
1/
#1000
0/
b0 4
01
#1500
b10 h
b1 %
b1 =
b1 O
b1 V
b1 g
1/
#2000
b1 a
b10 h
1<
0/
1-
#2500
b10 a
b11 h
b1 (
b1 A
b1 R
b1 X
b1 `
b10 %
b10 =
b10 O
b10 V
b10 g
1/
#3000
b1 a
b11 h
0<
0/
0-
#3500
b100 h
b11 %
b11 =
b11 O
b11 V
b11 g
1/
#4000
b1 c
b100 h
1;
0/
1.
#4500
b10 c
b101 h
b1 '
b1 ?
b1 Q
b1 W
b1 b
b100 %
b100 =
b100 O
b100 V
b100 g
1/
#5000
b1 c
b101 h
0;
0/
b1 4
0.
#5500
b110 h
b101 %
b101 =
b101 O
b101 V
b101 g
1/
#6000
b10 a
b110 h
1<
0/
1-
#6500
b11 a
b111 h
b10 (
b10 A
b10 R
b10 X
b10 `
b110 %
b110 =
b110 O
b110 V
b110 g
1/
#7000
b10 a
b111 h
0<
0/
0-
#7500
b1000 h
b111 %
b111 =
b111 O
b111 V
b111 g
1/
#8000
b10 c
b1000 h
1;
0/
1.
#8500
b11 c
b1001 h
b10 '
b10 ?
b10 Q
b10 W
b10 b
b1000 %
b1000 =
b1000 O
b1000 V
b1000 g
1/
#9000
b10 c
b1001 h
0;
0/
b10 4
0.
#9500
b1010 h
b1001 %
b1001 =
b1001 O
b1001 V
b1001 g
1/
#10000
b11 a
b1010 h
1<
0/
1-
#10500
b100 a
b1011 h
b11 (
b11 A
b11 R
b11 X
b11 `
b1010 %
b1010 =
b1010 O
b1010 V
b1010 g
1/
#11000
b11 a
b1011 h
0<
0/
0-
#11500
b1100 h
b1011 %
b1011 =
b1011 O
b1011 V
b1011 g
1/
#12000
b11 c
b1100 h
1;
0/
1.
#12500
b100 c
b1101 h
b11 '
b11 ?
b11 Q
b11 W
b11 b
b1100 %
b1100 =
b1100 O
b1100 V
b1100 g
1/
#13000
b11 c
b1101 h
0;
0/
b11 4
0.
#13500
b1110 h
b1101 %
b1101 =
b1101 O
b1101 V
b1101 g
1/
#14000
b100 a
b1110 h
1<
0/
1-
#14500
b101 a
b1111 h
b100 (
b100 A
b100 R
b100 X
b100 `
b1110 %
b1110 =
b1110 O
b1110 V
b1110 g
1/
#15000
b100 a
b1111 h
0<
0/
0-
#15500
b10000 h
b1111 %
b1111 =
b1111 O
b1111 V
b1111 g
1/
#16000
b100 c
b10000 h
1;
0/
1.
#16500
b101 c
b10001 h
b100 '
b100 ?
b100 Q
b100 W
b100 b
b10000 %
b10000 =
b10000 O
b10000 V
b10000 g
1/
#17000
b100 c
b10001 h
0;
0/
b100 4
0.
#17500
b10010 h
b10001 %
b10001 =
b10001 O
b10001 V
b10001 g
1/
#18000
b101 a
b10010 h
1<
0/
1-
#18500
b110 a
b10011 h
b101 (
b101 A
b101 R
b101 X
b101 `
b10010 %
b10010 =
b10010 O
b10010 V
b10010 g
1/
#19000
b101 a
b10011 h
0<
0/
0-
#19500
b10100 h
b10011 %
b10011 =
b10011 O
b10011 V
b10011 g
1/
#20000
b101 c
b10100 h
1;
0/
1.
#20500
b110 c
b10101 h
b101 '
b101 ?
b101 Q
b101 W
b101 b
b10100 %
b10100 =
b10100 O
b10100 V
b10100 g
1/
#21000
b101 c
b10101 h
0;
0/
b101 4
0.
#21500
b10110 h
b10101 %
b10101 =
b10101 O
b10101 V
b10101 g
1/
#22000
b110 a
b10110 h
1<
0/
1-
#22500
b111 a
b10111 h
b110 (
b110 A
b110 R
b110 X
b110 `
b10110 %
b10110 =
b10110 O
b10110 V
b10110 g
1/
#23000
b110 a
b10111 h
0<
0/
0-
#23500
b11000 h
b10111 %
b10111 =
b10111 O
b10111 V
b10111 g
1/
#24000
b110 c
b11000 h
1;
0/
1.
#24500
b111 c
b11001 h
b110 '
b110 ?
b110 Q
b110 W
b110 b
b11000 %
b11000 =
b11000 O
b11000 V
b11000 g
1/
#25000
b110 c
b11001 h
0;
0/
b110 4
0.
#25500
b11010 h
b11001 %
b11001 =
b11001 O
b11001 V
b11001 g
1/
#26000
b111 a
b11010 h
1<
0/
1-
#26500
b1000 a
b11011 h
b111 (
b111 A
b111 R
b111 X
b111 `
b11010 %
b11010 =
b11010 O
b11010 V
b11010 g
1/
#27000
b111 a
b11011 h
0<
0/
0-
#27500
b11100 h
b11011 %
b11011 =
b11011 O
b11011 V
b11011 g
1/
#28000
b111 c
b11100 h
1;
0/
1.
#28500
b1000 c
b11101 h
b111 '
b111 ?
b111 Q
b111 W
b111 b
b11100 %
b11100 =
b11100 O
b11100 V
b11100 g
1/
#29000
b111 c
b11101 h
0;
0/
b111 4
0.
#29500
b11110 h
b11101 %
b11101 =
b11101 O
b11101 V
b11101 g
1/
#30000
b1000 a
b11110 h
1<
0/
1-
#30500
b1001 a
b11111 h
b1000 (
b1000 A
b1000 R
b1000 X
b1000 `
b11110 %
b11110 =
b11110 O
b11110 V
b11110 g
1/
#31000
b1000 a
b11111 h
0<
0/
0-
#31500
b100000 h
b11111 %
b11111 =
b11111 O
b11111 V
b11111 g
1/
#32000
b1000 c
b100000 h
1;
0/
1.
#32500
b1001 c
b100001 h
b1000 '
b1000 ?
b1000 Q
b1000 W
b1000 b
b100000 %
b100000 =
b100000 O
b100000 V
b100000 g
1/
#33000
b1000 c
b100001 h
0;
0/
b1000 4
0.
#33500
b100010 h
b100001 %
b100001 =
b100001 O
b100001 V
b100001 g
1/
#34000
b1001 a
b100010 h
1<
0/
1-
#34500
b1010 a
b100011 h
b1001 (
b1001 A
b1001 R
b1001 X
b1001 `
b100010 %
b100010 =
b100010 O
b100010 V
b100010 g
1/
#35000
b1001 a
b100011 h
0<
0/
0-
#35500
b100100 h
b100011 %
b100011 =
b100011 O
b100011 V
b100011 g
1/
#36000
b1001 c
b100100 h
1;
0/
1.
#36500
b1010 c
b100101 h
b1001 '
b1001 ?
b1001 Q
b1001 W
b1001 b
b100100 %
b100100 =
b100100 O
b100100 V
b100100 g
1/
#37000
b1001 c
b100101 h
0;
0/
b1001 4
0.
#37500
b100110 h
b100101 %
b100101 =
b100101 O
b100101 V
b100101 g
1/
#38000
b1010 a
b100110 h
1<
0/
1-
#38500
b1011 a
b100111 h
b1010 (
b1010 A
b1010 R
b1010 X
b1010 `
b100110 %
b100110 =
b100110 O
b100110 V
b100110 g
1/
#39000
b1010 a
b100111 h
0<
0/
0-
#39500
b101000 h
b100111 %
b100111 =
b100111 O
b100111 V
b100111 g
1/
#40000
b1010 c
b101000 h
1;
0/
1.
#40500
b1011 c
b101001 h
b1010 '
b1010 ?
b1010 Q
b1010 W
b1010 b
b101000 %
b101000 =
b101000 O
b101000 V
b101000 g
1/
#41000
b1010 c
b101001 h
0;
0/
b1010 4
0.
#41500
b101010 h
b101001 %
b101001 =
b101001 O
b101001 V
b101001 g
1/
#42000
b1011 a
b101010 h
1<
0/
1-
#42500
1[
b1100 a
b101011 h
b1011 (
b1011 A
b1011 R
b1011 X
b1011 `
b101010 %
b101010 =
b101010 O
b101010 V
b101010 g
1/
#43000
0[
b1011 a
b101011 h
0<
0/
0-
#43500
b101100 h
b101011 %
b101011 =
b101011 O
b101011 V
b101011 g
1/
#44000
b1011 c
b101100 h
1;
0/
1.
#44500
b1100 c
b101101 h
b1011 '
b1011 ?
b1011 Q
b1011 W
b1011 b
b101100 %
b101100 =
b101100 O
b101100 V
b101100 g
1/
#45000
b1011 c
b101101 h
0;
0/
b1011 4
0.
#45500
b101110 h
b101101 %
b101101 =
b101101 O
b101101 V
b101101 g
1/
#46000
1[
b1100 a
b101110 h
1<
0/
1-
#46500
b1 a
b101111 h
1+
b1100 (
b1100 A
b1100 R
b1100 X
b1100 `
b101110 %
b101110 =
b101110 O
b101110 V
b101110 g
1/
#47000
b1100 a
b101111 h
0<
0/
0-
#47500
b110000 h
b101111 %
b101111 =
b101111 O
b101111 V
b101111 g
1/
#48000
b1100 c
b110000 h
1;
0/
1.
#48500
b1101 c
b110001 h
b1100 '
b1100 ?
b1100 Q
b1100 W
b1100 b
b110000 %
b110000 =
b110000 O
b110000 V
b110000 g
1/
#49000
b1100 c
b110001 h
0;
0/
b1100 4
0.
#49500
b110010 h
b110001 %
b110001 =
b110001 O
b110001 V
b110001 g
1/
#50000
b1 a
b110010 h
1<
0/
1-
#50500
b10 a
b110011 h
b1 (
b1 A
b1 R
b1 X
b1 `
b110010 %
b110010 =
b110010 O
b110010 V
b110010 g
1/
#51000
b1 a
b110011 h
0<
0/
0-
#51500
b110100 h
b110011 %
b110011 =
b110011 O
b110011 V
b110011 g
1/
#52000
b1101 c
b110100 h
1;
0/
1.
#52500
b1110 c
b110101 h
b1101 '
b1101 ?
b1101 Q
b1101 W
b1101 b
b110100 %
b110100 =
b110100 O
b110100 V
b110100 g
1/
#53000
b1101 c
b110101 h
0;
0/
b1101 4
0.
#53500
b110110 h
b110101 %
b110101 =
b110101 O
b110101 V
b110101 g
1/
#54000
b10 a
b110110 h
1<
0/
1-
#54500
b11 a
b110111 h
b10 (
b10 A
b10 R
b10 X
b10 `
b110110 %
b110110 =
b110110 O
b110110 V
b110110 g
1/
#55000
b10 a
b110111 h
0<
0/
0-
#55500
b111000 h
b110111 %
b110111 =
b110111 O
b110111 V
b110111 g
1/
#56000
b1110 c
b111000 h
1;
0/
1.
#56500
b1111 c
b111001 h
b1110 '
b1110 ?
b1110 Q
b1110 W
b1110 b
b111000 %
b111000 =
b111000 O
b111000 V
b111000 g
1/
#57000
b1110 c
b111001 h
0;
0/
b1110 4
0.
#57500
b111010 h
b111001 %
b111001 =
b111001 O
b111001 V
b111001 g
1/
#58000
b11 a
b111010 h
1<
0/
1-
#58500
b100 a
b111011 h
b11 (
b11 A
b11 R
b11 X
b11 `
b111010 %
b111010 =
b111010 O
b111010 V
b111010 g
1/
#59000
b11 a
b111011 h
0<
0/
0-
#59500
b1 f
b0 h
b111011 %
b111011 =
b111011 O
b111011 V
b111011 g
1/
#60000
b1111 c
b0 h
b1 f
1;
0/
1.
#60500
b0 f
b10000 c
b1111 '
b1111 ?
b1111 Q
b1111 W
b1111 b
b0 %
b0 =
b0 O
b0 V
b0 g
b1 i
1/
#61000
b10000 c
b0 f
0;
0/
b1111 4
0.
#61500
b1 h
b10000 '
b10000 ?
b10000 Q
b10000 W
b10000 b
b0 i
1/
#62000
b100 a
b1 h
1<
0/
1-
#62500
b101 a
b10 h
b100 (
b100 A
b100 R
b100 X
b100 `
b1 %
b1 =
b1 O
b1 V
b1 g
1/
#63000
b100 a
b10 h
0<
0/
0-
#63500
b11 h
b10 %
b10 =
b10 O
b10 V
b10 g
1/
#64000
b10001 c
b11 h
1;
0/
1.
#64500
b10010 c
b100 h
b10001 '
b10001 ?
b10001 Q
b10001 W
b10001 b
b11 %
b11 =
b11 O
b11 V
b11 g
1/
#65000
b10001 c
b100 h
0;
0/
b10000 4
0.
#65500
b101 h
b100 %
b100 =
b100 O
b100 V
b100 g
1/
#66000
b101 a
b101 h
1<
0/
1-
#66500
b110 a
b110 h
b101 (
b101 A
b101 R
b101 X
b101 `
b101 %
b101 =
b101 O
b101 V
b101 g
1/
#67000
b101 a
b110 h
0<
0/
0-
#67500
b111 h
b110 %
b110 =
b110 O
b110 V
b110 g
1/
#68000
b10010 c
b111 h
1;
0/
1.
#68500
b10011 c
b1000 h
b10010 '
b10010 ?
b10010 Q
b10010 W
b10010 b
b111 %
b111 =
b111 O
b111 V
b111 g
1/
#69000
b10010 c
b1000 h
0;
0/
b10001 4
0.
#69500
b1001 h
b1000 %
b1000 =
b1000 O
b1000 V
b1000 g
1/
#70000
b110 a
b1001 h
1<
0/
1-
#70500
b111 a
b1010 h
b110 (
b110 A
b110 R
b110 X
b110 `
b1001 %
b1001 =
b1001 O
b1001 V
b1001 g
1/
#71000
b110 a
b1010 h
0<
0/
0-
#71500
b1011 h
b1010 %
b1010 =
b1010 O
b1010 V
b1010 g
1/
#72000
b10011 c
b1011 h
1;
0/
1.
#72500
b10100 c
b1100 h
b10011 '
b10011 ?
b10011 Q
b10011 W
b10011 b
b1011 %
b1011 =
b1011 O
b1011 V
b1011 g
1/
#73000
b10011 c
b1100 h
0;
0/
b10010 4
0.
#73500
b1101 h
b1100 %
b1100 =
b1100 O
b1100 V
b1100 g
1/
#74000
b111 a
b1101 h
1<
0/
1-
#74500
b1000 a
b1110 h
b111 (
b111 A
b111 R
b111 X
b111 `
b1101 %
b1101 =
b1101 O
b1101 V
b1101 g
1/
#75000
b111 a
b1110 h
0<
0/
0-
#75500
b1111 h
b1110 %
b1110 =
b1110 O
b1110 V
b1110 g
1/
#76000
b10100 c
b1111 h
1;
0/
1.
#76500
b10101 c
b10000 h
b10100 '
b10100 ?
b10100 Q
b10100 W
b10100 b
b1111 %
b1111 =
b1111 O
b1111 V
b1111 g
1/
#77000
b10100 c
b10000 h
0;
0/
b10011 4
0.
